{
"meta":{"test_sets":[],"test_metrics":[],"learn_metrics":[{"best_value":"Min","name":"Logloss"}],"launch_mode":"Train","parameters":"","iteration_count":1000,"learn_sets":["learn"],"name":"experiment"},
"iterations":[
{"learn":[0.5999904035],"iteration":0,"passed_time":0.03979048111,"remaining_time":39.75069063},
{"learn":[0.5326434809],"iteration":1,"passed_time":0.05676655361,"remaining_time":28.32651025},
{"learn":[0.4757951094],"iteration":2,"passed_time":0.07147807716,"remaining_time":23.75454764},
{"learn":[0.4350614118],"iteration":3,"passed_time":0.0853977882,"remaining_time":21.26404926},
{"learn":[0.401300368],"iteration":4,"passed_time":0.09926289968,"remaining_time":19.75331704},
{"learn":[0.3755787716],"iteration":5,"passed_time":0.1116580826,"remaining_time":18.49802236},
{"learn":[0.3536818201],"iteration":6,"passed_time":0.1245179557,"remaining_time":17.66376144},
{"learn":[0.3391746073],"iteration":7,"passed_time":0.1366945859,"remaining_time":16.95012865},
{"learn":[0.3210548074],"iteration":8,"passed_time":0.1480906328,"remaining_time":16.30642412},
{"learn":[0.3056375642],"iteration":9,"passed_time":0.1593668737,"remaining_time":15.7773205},
{"learn":[0.294214665],"iteration":10,"passed_time":0.1709953295,"remaining_time":15.37403463},
{"learn":[0.2846278086],"iteration":11,"passed_time":0.1827675642,"remaining_time":15.04786279},
{"learn":[0.2770123901],"iteration":12,"passed_time":0.1940491826,"remaining_time":14.73281102},
{"learn":[0.2678133285],"iteration":13,"passed_time":0.2057890655,"remaining_time":14.4934299},
{"learn":[0.2579471313],"iteration":14,"passed_time":0.2170443031,"remaining_time":14.2525759},
{"learn":[0.2514909068],"iteration":15,"passed_time":0.2287631366,"remaining_time":14.0689329},
{"learn":[0.2421735334],"iteration":16,"passed_time":0.2399107892,"remaining_time":13.87248858},
{"learn":[0.2372168296],"iteration":17,"passed_time":0.2511934297,"remaining_time":13.70399711},
{"learn":[0.2308260629],"iteration":18,"passed_time":0.2631753662,"remaining_time":13.5881597},
{"learn":[0.2257463362],"iteration":19,"passed_time":0.2748386723,"remaining_time":13.46709494},
{"learn":[0.2222723544],"iteration":20,"passed_time":0.2861534686,"remaining_time":13.34020218},
{"learn":[0.2188705642],"iteration":21,"passed_time":0.2986401795,"remaining_time":13.27591343},
{"learn":[0.2154334639],"iteration":22,"passed_time":0.3093032363,"remaining_time":13.13866356},
{"learn":[0.2116725856],"iteration":23,"passed_time":0.3205773003,"remaining_time":13.03681021},
{"learn":[0.2086196929],"iteration":24,"passed_time":0.331460785,"remaining_time":12.92697062},
{"learn":[0.2056700434],"iteration":25,"passed_time":0.3425049974,"remaining_time":12.83076413},
{"learn":[0.2034705362],"iteration":26,"passed_time":0.3534548037,"remaining_time":12.73746385},
{"learn":[0.2007618117],"iteration":27,"passed_time":0.364470114,"remaining_time":12.65231967},
{"learn":[0.1987502541],"iteration":28,"passed_time":0.3758741731,"remaining_time":12.58530421},
{"learn":[0.1968629535],"iteration":29,"passed_time":0.3871713699,"remaining_time":12.51854096},
{"learn":[0.1942177407],"iteration":30,"passed_time":0.3986277004,"remaining_time":12.46033038},
{"learn":[0.1911997013],"iteration":31,"passed_time":0.4097780692,"remaining_time":12.39578659},
{"learn":[0.1890501002],"iteration":32,"passed_time":0.4208809624,"remaining_time":12.3330876},
{"learn":[0.1873460449],"iteration":33,"passed_time":0.4320441914,"remaining_time":12.27513791},
{"learn":[0.1857842646],"iteration":34,"passed_time":0.443272486,"remaining_time":12.22165569},
{"learn":[0.184288653],"iteration":35,"passed_time":0.4550485728,"remaining_time":12.18518956},
{"learn":[0.1807019615],"iteration":36,"passed_time":0.4661997767,"remaining_time":12.13379419},
{"learn":[0.1791574836],"iteration":37,"passed_time":0.477132187,"remaining_time":12.078978},
{"learn":[0.1772834843],"iteration":38,"passed_time":0.4881802697,"remaining_time":12.02926254},
{"learn":[0.1759132185],"iteration":39,"passed_time":0.4989220451,"remaining_time":11.97412908},
{"learn":[0.1733693004],"iteration":40,"passed_time":0.5100132299,"remaining_time":11.92933384},
{"learn":[0.1724886703],"iteration":41,"passed_time":0.5210718049,"remaining_time":11.88539974},
{"learn":[0.1710446431],"iteration":42,"passed_time":0.5321889408,"remaining_time":11.84429805},
{"learn":[0.1698298531],"iteration":43,"passed_time":0.5432347891,"remaining_time":11.80301042},
{"learn":[0.1684508717],"iteration":44,"passed_time":0.5541288952,"remaining_time":11.75984655},
{"learn":[0.167706899],"iteration":45,"passed_time":0.5650354503,"remaining_time":11.7183439},
{"learn":[0.1666085546],"iteration":46,"passed_time":0.576000061,"remaining_time":11.67932039},
{"learn":[0.1653435447],"iteration":47,"passed_time":0.5869525096,"remaining_time":11.64122477},
{"learn":[0.1640125907],"iteration":48,"passed_time":0.598395492,"remaining_time":11.61375741},
{"learn":[0.1627600882],"iteration":49,"passed_time":0.6087913864,"remaining_time":11.56703634},
{"learn":[0.1610401183],"iteration":50,"passed_time":0.6198077905,"remaining_time":11.53328614},
{"learn":[0.1595081863],"iteration":51,"passed_time":0.6313249755,"remaining_time":11.50953994},
{"learn":[0.158701703],"iteration":52,"passed_time":0.6431037453,"remaining_time":11.49092919},
{"learn":[0.1580898726],"iteration":53,"passed_time":0.654209914,"remaining_time":11.46078849},
{"learn":[0.1570860442],"iteration":54,"passed_time":0.6651440822,"remaining_time":11.42838469},
{"learn":[0.155815708],"iteration":55,"passed_time":0.6761829372,"remaining_time":11.39851237},
{"learn":[0.1545907778],"iteration":56,"passed_time":0.6877198797,"remaining_time":11.37754117},
{"learn":[0.1533953964],"iteration":57,"passed_time":0.6991835954,"remaining_time":11.35570598},
{"learn":[0.1525050674],"iteration":58,"passed_time":0.7107091185,"remaining_time":11.33520814},
{"learn":[0.1519598712],"iteration":59,"passed_time":0.7216112732,"remaining_time":11.30524328},
{"learn":[0.1513116608],"iteration":60,"passed_time":0.7324806177,"remaining_time":11.27539836},
{"learn":[0.1505091245],"iteration":61,"passed_time":0.7437736929,"remaining_time":11.25257619},
{"learn":[0.1496776179],"iteration":62,"passed_time":0.7550826065,"remaining_time":11.23035559},
{"learn":[0.1489148802],"iteration":63,"passed_time":0.7656647622,"remaining_time":11.19784715},
{"learn":[0.1484547677],"iteration":64,"passed_time":0.7768009622,"remaining_time":11.17398307},
{"learn":[0.1479406213],"iteration":65,"passed_time":0.7882422734,"remaining_time":11.15482247},
{"learn":[0.1472776813],"iteration":66,"passed_time":0.8004009918,"remaining_time":11.14588247},
{"learn":[0.1463914589],"iteration":67,"passed_time":0.8119168592,"remaining_time":11.12803695},
{"learn":[0.1456309075],"iteration":68,"passed_time":0.823626299,"remaining_time":11.11298673},
{"learn":[0.1451316327],"iteration":69,"passed_time":0.8357688712,"remaining_time":11.10378643},
{"learn":[0.144643645],"iteration":70,"passed_time":0.8479761679,"remaining_time":11.09535014},
{"learn":[0.1434278775],"iteration":71,"passed_time":0.8603971204,"remaining_time":11.08956288},
{"learn":[0.1428047261],"iteration":72,"passed_time":0.8717956026,"remaining_time":11.07060991},
{"learn":[0.1419970715],"iteration":73,"passed_time":0.8832048325,"remaining_time":11.05199561},
{"learn":[0.1413119597],"iteration":74,"passed_time":0.8949270403,"remaining_time":11.0374335},
{"learn":[0.1408033286],"iteration":75,"passed_time":0.9069160038,"remaining_time":11.02618931},
{"learn":[0.1404288526],"iteration":76,"passed_time":0.9188569157,"remaining_time":11.01434978},
{"learn":[0.1398649949],"iteration":77,"passed_time":0.9319173699,"remaining_time":11.01574122},
{"learn":[0.1394177866],"iteration":78,"passed_time":0.9448080145,"remaining_time":11.01478711},
{"learn":[0.1387074658],"iteration":79,"passed_time":0.9569030176,"remaining_time":11.0043847},
{"learn":[0.1373700226],"iteration":80,"passed_time":0.9687659608,"remaining_time":10.99130763},
{"learn":[0.1366317951],"iteration":81,"passed_time":0.9796935175,"remaining_time":10.9677884},
{"learn":[0.1359301816],"iteration":82,"passed_time":0.9908537697,"remaining_time":10.94714346},
{"learn":[0.1355035932],"iteration":83,"passed_time":1.001406477,"remaining_time":10.9200992},
{"learn":[0.135119475],"iteration":84,"passed_time":1.01243626,"remaining_time":10.89857856},
{"learn":[0.1343842182],"iteration":85,"passed_time":1.023459174,"remaining_time":10.87722889},
{"learn":[0.133914783],"iteration":86,"passed_time":1.033945153,"remaining_time":10.8504819},
{"learn":[0.1333471029],"iteration":87,"passed_time":1.047260947,"remaining_time":10.85343164},
{"learn":[0.1326620645],"iteration":88,"passed_time":1.062459562,"remaining_time":10.87528832},
{"learn":[0.1323878695],"iteration":89,"passed_time":1.073953457,"remaining_time":10.85886273},
{"learn":[0.1317021675],"iteration":90,"passed_time":1.085296255,"remaining_time":10.84103622},
{"learn":[0.1312757205],"iteration":91,"passed_time":1.095981675,"remaining_time":10.81686262},
{"learn":[0.1307302076],"iteration":92,"passed_time":1.107433612,"remaining_time":10.80045469},
{"learn":[0.1302281264],"iteration":93,"passed_time":1.118753019,"remaining_time":10.78287485},
{"learn":[0.1298833502],"iteration":94,"passed_time":1.129815247,"remaining_time":10.76297683},
{"learn":[0.129379064],"iteration":95,"passed_time":1.142217381,"remaining_time":10.75588034},
{"learn":[0.1288806707],"iteration":96,"passed_time":1.153974792,"remaining_time":10.74267255},
{"learn":[0.1281533732],"iteration":97,"passed_time":1.165255828,"remaining_time":10.72510977},
{"learn":[0.1277160137],"iteration":98,"passed_time":1.176522842,"remaining_time":10.70754627},
{"learn":[0.1274401768],"iteration":99,"passed_time":1.187845471,"remaining_time":10.69060924},
{"learn":[0.1270814032],"iteration":100,"passed_time":1.199675303,"remaining_time":10.67829799},
{"learn":[0.1266759264],"iteration":101,"passed_time":1.21259413,"remaining_time":10.67558361},
{"learn":[0.1261851161],"iteration":102,"passed_time":1.225496986,"remaining_time":10.67253201},
{"learn":[0.1259520135],"iteration":103,"passed_time":1.23775577,"remaining_time":10.66374202},
{"learn":[0.125605234],"iteration":104,"passed_time":1.249707629,"remaining_time":10.65226979},
{"learn":[0.1253030948],"iteration":105,"passed_time":1.262697361,"remaining_time":10.64954189},
{"learn":[0.1251025966],"iteration":106,"passed_time":1.275340008,"remaining_time":10.64372549},
{"learn":[0.1247569213],"iteration":107,"passed_time":1.287850313,"remaining_time":10.63668962},
{"learn":[0.1244160786],"iteration":108,"passed_time":1.299650034,"remaining_time":10.62374477},
{"learn":[0.1239006115],"iteration":109,"passed_time":1.313165251,"remaining_time":10.62470066},
{"learn":[0.1235829307],"iteration":110,"passed_time":1.32586832,"remaining_time":10.61889132},
{"learn":[0.1232132514],"iteration":111,"passed_time":1.33887566,"remaining_time":10.6153713},
{"learn":[0.1226022142],"iteration":112,"passed_time":1.351429484,"remaining_time":10.60812347},
{"learn":[0.1222210508],"iteration":113,"passed_time":1.363810822,"remaining_time":10.599442},
{"learn":[0.1219640699],"iteration":114,"passed_time":1.376625929,"remaining_time":10.59403432},
{"learn":[0.1216237309],"iteration":115,"passed_time":1.388935888,"remaining_time":10.58464935},
{"learn":[0.1214454563],"iteration":116,"passed_time":1.402527041,"remaining_time":10.58488357},
{"learn":[0.1210740916],"iteration":117,"passed_time":1.416472712,"remaining_time":10.58753332},
{"learn":[0.1207866052],"iteration":118,"passed_time":1.429283257,"remaining_time":10.58150041},
{"learn":[0.1204398424],"iteration":119,"passed_time":1.442087178,"remaining_time":10.57530597},
{"learn":[0.1199377559],"iteration":120,"passed_time":1.455230161,"remaining_time":10.57146539},
{"learn":[0.1196950429],"iteration":121,"passed_time":1.467802917,"remaining_time":10.56336853},
{"learn":[0.1193892767],"iteration":122,"passed_time":1.480681212,"remaining_time":10.55737743},
{"learn":[0.1191048443],"iteration":123,"passed_time":1.493110364,"remaining_time":10.54810225},
{"learn":[0.1189070681],"iteration":124,"passed_time":1.505052858,"remaining_time":10.53537001},
{"learn":[0.1184921999],"iteration":125,"passed_time":1.518435433,"remaining_time":10.53263943},
{"learn":[0.1181305865],"iteration":126,"passed_time":1.531898689,"remaining_time":10.53029571},
{"learn":[0.1177195938],"iteration":127,"passed_time":1.542750596,"remaining_time":10.50998843},
{"learn":[0.1174051717],"iteration":128,"passed_time":1.553708763,"remaining_time":10.49054522},
{"learn":[0.1169337372],"iteration":129,"passed_time":1.564889608,"remaining_time":10.47272276},
{"learn":[0.1168027789],"iteration":130,"passed_time":1.576013808,"remaining_time":10.45462594},
{"learn":[0.1166299608],"iteration":131,"passed_time":1.587030902,"remaining_time":10.43593048},
{"learn":[0.1163028424],"iteration":132,"passed_time":1.598058623,"remaining_time":10.41741975},
{"learn":[0.1159428566],"iteration":133,"passed_time":1.609347608,"remaining_time":10.40070917},
{"learn":[0.1155223311],"iteration":134,"passed_time":1.619950482,"remaining_time":10.37968272},
{"learn":[0.1153490845],"iteration":135,"passed_time":1.631058016,"remaining_time":10.36201563},
{"learn":[0.114978063],"iteration":136,"passed_time":1.641861258,"remaining_time":10.34252749},
{"learn":[0.1146925028],"iteration":137,"passed_time":1.653023665,"remaining_time":10.32540869},
{"learn":[0.1145469291],"iteration":138,"passed_time":1.664039464,"remaining_time":10.30746747},
{"learn":[0.1141698549],"iteration":139,"passed_time":1.675419625,"remaining_time":10.29186341},
{"learn":[0.1138797496],"iteration":140,"passed_time":1.686685237,"remaining_time":10.27562141},
{"learn":[0.1136801007],"iteration":141,"passed_time":1.697115342,"remaining_time":10.25440115},
{"learn":[0.1134969062],"iteration":142,"passed_time":1.706990876,"remaining_time":10.23000826},
{"learn":[0.1132504231],"iteration":143,"passed_time":1.717899916,"remaining_time":10.21196061},
{"learn":[0.1130436862],"iteration":144,"passed_time":1.728798657,"remaining_time":10.1939507},
{"learn":[0.1127388549],"iteration":145,"passed_time":1.739815844,"remaining_time":10.17673103},
{"learn":[0.1126157006],"iteration":146,"passed_time":1.750152581,"remaining_time":10.15564729},
{"learn":[0.1124574364],"iteration":147,"passed_time":1.761075486,"remaining_time":10.1380832},
{"learn":[0.1122422599],"iteration":148,"passed_time":1.773099235,"remaining_time":10.12689563},
{"learn":[0.1120776894],"iteration":149,"passed_time":1.787248981,"remaining_time":10.12774423},
{"learn":[0.1118281009],"iteration":150,"passed_time":1.800617211,"remaining_time":10.12400008},
{"learn":[0.1116608938],"iteration":151,"passed_time":1.813982217,"remaining_time":10.12011131},
{"learn":[0.1114601927],"iteration":152,"passed_time":1.827166643,"remaining_time":10.115099},
{"learn":[0.1111154889],"iteration":153,"passed_time":1.841555245,"remaining_time":10.11659569},
{"learn":[0.110803261],"iteration":154,"passed_time":1.855469455,"remaining_time":10.11530122},
{"learn":[0.1106199844],"iteration":155,"passed_time":1.869725724,"remaining_time":10.11569558},
{"learn":[0.110401071],"iteration":156,"passed_time":1.882170418,"remaining_time":10.10617619},
{"learn":[0.1101930733],"iteration":157,"passed_time":1.894504983,"remaining_time":10.09603288},
{"learn":[0.1098694706],"iteration":158,"passed_time":1.906706166,"remaining_time":10.08515651},
{"learn":[0.109719328],"iteration":159,"passed_time":1.918417914,"remaining_time":10.07169405},
{"learn":[0.1095056682],"iteration":160,"passed_time":1.931892617,"remaining_time":10.06744041},
{"learn":[0.1092553225],"iteration":161,"passed_time":1.944503093,"remaining_time":10.05860242},
{"learn":[0.1090172093],"iteration":162,"passed_time":1.958201797,"remaining_time":10.05530616},
{"learn":[0.1088514655],"iteration":163,"passed_time":1.970988282,"remaining_time":10.04723295},
{"learn":[0.1086522259],"iteration":164,"passed_time":1.983588425,"remaining_time":10.03815961},
{"learn":[0.1084723532],"iteration":165,"passed_time":1.996118769,"remaining_time":10.02869309},
{"learn":[0.1082882057],"iteration":166,"passed_time":2.009647401,"remaining_time":10.02416937},
{"learn":[0.108036336],"iteration":167,"passed_time":2.022510392,"remaining_time":10.01624194},
{"learn":[0.1079881137],"iteration":168,"passed_time":2.033782833,"remaining_time":10.00043511},
{"learn":[0.1077911116],"iteration":169,"passed_time":2.048823693,"remaining_time":10.00308038},
{"learn":[0.1076507164],"iteration":170,"passed_time":2.066581834,"remaining_time":10.01869205},
{"learn":[0.1075093078],"iteration":171,"passed_time":2.080987628,"remaining_time":10.01777765},
{"learn":[0.1073647532],"iteration":172,"passed_time":2.094125863,"remaining_time":10.01064791},
{"learn":[0.1071046217],"iteration":173,"passed_time":2.106625456,"remaining_time":10.0004174},
{"learn":[0.1069240805],"iteration":174,"passed_time":2.119769036,"remaining_time":9.993196885},
{"learn":[0.1066827994],"iteration":175,"passed_time":2.133354581,"remaining_time":9.987978265},
{"learn":[0.1065652755],"iteration":176,"passed_time":2.145525993,"remaining_time":9.976089789},
{"learn":[0.1064226466],"iteration":177,"passed_time":2.158315725,"remaining_time":9.967053518},
{"learn":[0.1062571583],"iteration":178,"passed_time":2.171342182,"remaining_time":9.959061068},
{"learn":[0.1060768378],"iteration":179,"passed_time":2.184425094,"remaining_time":9.951269871},
{"learn":[0.1059541077],"iteration":180,"passed_time":2.197171525,"remaining_time":9.941897676},
{"learn":[0.1057898077],"iteration":181,"passed_time":2.209299225,"remaining_time":9.929707504},
{"learn":[0.1056827958],"iteration":182,"passed_time":2.222083264,"remaining_time":9.920448235},
{"learn":[0.1054747422],"iteration":183,"passed_time":2.234825355,"remaining_time":9.910964619},
{"learn":[0.1053206477],"iteration":184,"passed_time":2.247018818,"remaining_time":9.899028847},
{"learn":[0.1051197812],"iteration":185,"passed_time":2.259886336,"remaining_time":9.890040203},
{"learn":[0.1049967978],"iteration":186,"passed_time":2.272904374,"remaining_time":9.881664471},
{"learn":[0.104851297],"iteration":187,"passed_time":2.285857885,"remaining_time":9.872960653},
{"learn":[0.1047679174],"iteration":188,"passed_time":2.298372614,"remaining_time":9.862329047},
{"learn":[0.104606475],"iteration":189,"passed_time":2.311017432,"remaining_time":9.852232209},
{"learn":[0.1044241765],"iteration":190,"passed_time":2.323510951,"remaining_time":9.841467849},
{"learn":[0.1042936686],"iteration":191,"passed_time":2.336189968,"remaining_time":9.831466117},
{"learn":[0.1041392304],"iteration":192,"passed_time":2.348647707,"remaining_time":9.820511395},
{"learn":[0.1040575127],"iteration":193,"passed_time":2.360664706,"remaining_time":9.807710066},
{"learn":[0.103900184],"iteration":194,"passed_time":2.374069189,"remaining_time":9.800644602},
{"learn":[0.1038022923],"iteration":195,"passed_time":2.38702677,"remaining_time":9.791681241},
{"learn":[0.1036427578],"iteration":196,"passed_time":2.399893059,"remaining_time":9.782305209},
{"learn":[0.1035382042],"iteration":197,"passed_time":2.411829139,"remaining_time":9.76912611},
{"learn":[0.1033728182],"iteration":198,"passed_time":2.424671936,"remaining_time":9.75960915},
{"learn":[0.1032361063],"iteration":199,"passed_time":2.438035972,"remaining_time":9.752143886},
{"learn":[0.1031578965],"iteration":200,"passed_time":2.450257914,"remaining_time":9.740079966},
{"learn":[0.1029747786],"iteration":201,"passed_time":2.462718563,"remaining_time":9.728957493},
{"learn":[0.102868259],"iteration":202,"passed_time":2.47661579,"remaining_time":9.723461992},
{"learn":[0.1027672793],"iteration":203,"passed_time":2.489417133,"remaining_time":9.713608028},
{"learn":[0.1026188962],"iteration":204,"passed_time":2.502337999,"remaining_time":9.704188827},
{"learn":[0.1024485958],"iteration":205,"passed_time":2.515431297,"remaining_time":9.695400244},
{"learn":[0.1023886564],"iteration":206,"passed_time":2.527916788,"remaining_time":9.684241609},
{"learn":[0.1022680179],"iteration":207,"passed_time":2.540991351,"remaining_time":9.675313222},
{"learn":[0.1022020583],"iteration":208,"passed_time":2.553720283,"remaining_time":9.665037052},
{"learn":[0.1021112365],"iteration":209,"passed_time":2.565455862,"remaining_time":9.651000622},
{"learn":[0.101986151],"iteration":210,"passed_time":2.577989183,"remaining_time":9.639969032},
{"learn":[0.1018331666],"iteration":211,"passed_time":2.591844542,"remaining_time":9.63383726},
{"learn":[0.101666983],"iteration":212,"passed_time":2.606558458,"remaining_time":9.630805195},
{"learn":[0.1015476177],"iteration":213,"passed_time":2.619052535,"remaining_time":9.619510714},
{"learn":[0.1013554048],"iteration":214,"passed_time":2.630455238,"remaining_time":9.604220286},
{"learn":[0.101250096],"iteration":215,"passed_time":2.641511574,"remaining_time":9.587708676},
{"learn":[0.1011641314],"iteration":216,"passed_time":2.652109127,"remaining_time":9.56959192},
{"learn":[0.1010685392],"iteration":217,"passed_time":2.663866726,"remaining_time":9.555705411},
{"learn":[0.1009229542],"iteration":218,"passed_time":2.674723749,"remaining_time":9.538626702},
{"learn":[0.1008631317],"iteration":219,"passed_time":2.6853539,"remaining_time":9.520800191},
{"learn":[0.1007130929],"iteration":220,"passed_time":2.69601829,"remaining_time":9.503159493},
{"learn":[0.1005192771],"iteration":221,"passed_time":2.707679453,"remaining_time":9.48907484},
{"learn":[0.1003881193],"iteration":222,"passed_time":2.71892526,"remaining_time":9.473564696},
{"learn":[0.1002871633],"iteration":223,"passed_time":2.730341171,"remaining_time":9.458681912},
{"learn":[0.1002040322],"iteration":224,"passed_time":2.74167343,"remaining_time":9.443541815},
{"learn":[0.1000694756],"iteration":225,"passed_time":2.752809867,"remaining_time":9.427764765},
{"learn":[0.09997961094],"iteration":226,"passed_time":2.76337196,"remaining_time":9.410072799},
{"learn":[0.09986438991],"iteration":227,"passed_time":2.776351037,"remaining_time":9.400627197},
{"learn":[0.09978631867],"iteration":228,"passed_time":2.788670657,"remaining_time":9.388930467},
{"learn":[0.09964240669],"iteration":229,"passed_time":2.802070288,"remaining_time":9.380844008},
{"learn":[0.09943479732],"iteration":230,"passed_time":2.814340894,"remaining_time":9.36895302},
{"learn":[0.09931321588],"iteration":231,"passed_time":2.827522095,"remaining_time":9.360073142},
{"learn":[0.09914830152],"iteration":232,"passed_time":2.840293165,"remaining_time":9.349806255},
{"learn":[0.09907751224],"iteration":233,"passed_time":2.851958917,"remaining_time":9.335899702},
{"learn":[0.09891512163],"iteration":234,"passed_time":2.862575365,"remaining_time":9.318596399},
{"learn":[0.0988420372],"iteration":235,"passed_time":2.873837508,"remaining_time":9.30344007},
{"learn":[0.09873160107],"iteration":236,"passed_time":2.885097692,"remaining_time":9.288310291},
{"learn":[0.09859256682],"iteration":237,"passed_time":2.896169106,"remaining_time":9.27260865},
{"learn":[0.09841887352],"iteration":238,"passed_time":2.907175177,"remaining_time":9.256737696},
{"learn":[0.09831872454],"iteration":239,"passed_time":2.91840368,"remaining_time":9.241611655},
{"learn":[0.09824767945],"iteration":240,"passed_time":2.92936146,"remaining_time":9.225665345},
{"learn":[0.09799398275],"iteration":241,"passed_time":2.940258357,"remaining_time":9.209569565},
{"learn":[0.09791327834],"iteration":242,"passed_time":2.951380464,"remaining_time":9.194218154},
{"learn":[0.09784605105],"iteration":243,"passed_time":2.96221204,"remaining_time":9.178001238},
{"learn":[0.09774235442],"iteration":244,"passed_time":2.973695351,"remaining_time":9.163836694},
{"learn":[0.09765259136],"iteration":245,"passed_time":2.984424502,"remaining_time":9.147382416},
{"learn":[0.09758143507],"iteration":246,"passed_time":2.994372367,"remaining_time":9.128592681},
{"learn":[0.09753287581],"iteration":247,"passed_time":3.004723933,"remaining_time":9.111098376},
{"learn":[0.09741427467],"iteration":248,"passed_time":3.01597605,"remaining_time":9.096377565},
{"learn":[0.09733702856],"iteration":249,"passed_time":3.027102241,"remaining_time":9.081306724},
{"learn":[0.09724632701],"iteration":250,"passed_time":3.037848912,"remaining_time":9.0651348},
{"learn":[0.09714728271],"iteration":251,"passed_time":3.048958365,"remaining_time":9.050082767},
{"learn":[0.09703228698],"iteration":252,"passed_time":3.062252073,"remaining_time":9.041511062},
{"learn":[0.09693615995],"iteration":253,"passed_time":3.075332518,"remaining_time":9.032275822},
{"learn":[0.09686203612],"iteration":254,"passed_time":3.086957251,"remaining_time":9.018757457},
{"learn":[0.09675124961],"iteration":255,"passed_time":3.097893866,"remaining_time":9.003254047},
{"learn":[0.09663115743],"iteration":256,"passed_time":3.109080161,"remaining_time":8.988508013},
{"learn":[0.09653148904],"iteration":257,"passed_time":3.120848444,"remaining_time":8.975463355},
{"learn":[0.09643562811],"iteration":258,"passed_time":3.131887298,"remaining_time":8.960341652},
{"learn":[0.09628414962],"iteration":259,"passed_time":3.143523905,"remaining_time":8.946952653},
{"learn":[0.09622755852],"iteration":260,"passed_time":3.153880115,"remaining_time":8.929951742},
{"learn":[0.09613168075],"iteration":261,"passed_time":3.16426599,"remaining_time":8.913085116},
{"learn":[0.09604286547],"iteration":262,"passed_time":3.174987518,"remaining_time":8.897208367},
{"learn":[0.09597167645],"iteration":263,"passed_time":3.185961717,"remaining_time":8.882075089},
{"learn":[0.09588863894],"iteration":264,"passed_time":3.196726814,"remaining_time":8.866393239},
{"learn":[0.09579122142],"iteration":265,"passed_time":3.207299695,"remaining_time":8.850217955},
{"learn":[0.09569967994],"iteration":266,"passed_time":3.218793308,"remaining_time":8.836612341},
{"learn":[0.09561575583],"iteration":267,"passed_time":3.230095349,"remaining_time":8.822499237},
{"learn":[0.09550646582],"iteration":268,"passed_time":3.241256754,"remaining_time":8.80802486},
{"learn":[0.0954309449],"iteration":269,"passed_time":3.253126226,"remaining_time":8.795489427},
{"learn":[0.09528452034],"iteration":270,"passed_time":3.264692657,"remaining_time":8.782143715},
{"learn":[0.09523447916],"iteration":271,"passed_time":3.275047965,"remaining_time":8.765569552},
{"learn":[0.09506792783],"iteration":272,"passed_time":3.286445214,"remaining_time":8.751815643},
{"learn":[0.09494960711],"iteration":273,"passed_time":3.297840008,"remaining_time":8.738072429},
{"learn":[0.0948541522],"iteration":274,"passed_time":3.309078858,"remaining_time":8.723935171},
{"learn":[0.09473104307],"iteration":275,"passed_time":3.322533246,"remaining_time":8.715630689},
{"learn":[0.09467533294],"iteration":276,"passed_time":3.333662408,"remaining_time":8.701219932},
{"learn":[0.0946231499],"iteration":277,"passed_time":3.344196175,"remaining_time":8.68528647},
{"learn":[0.0945604421],"iteration":278,"passed_time":3.354872007,"remaining_time":8.669758842},
{"learn":[0.0944922053],"iteration":279,"passed_time":3.365590489,"remaining_time":8.654375542},
{"learn":[0.09435524412],"iteration":280,"passed_time":3.377104997,"remaining_time":8.641062253},
{"learn":[0.09426096098],"iteration":281,"passed_time":3.388440696,"remaining_time":8.627306452},
{"learn":[0.09417484944],"iteration":282,"passed_time":3.400093461,"remaining_time":8.614371065},
{"learn":[0.09411045991],"iteration":283,"passed_time":3.411069579,"remaining_time":8.599738798},
{"learn":[0.09401160371],"iteration":284,"passed_time":3.421980863,"remaining_time":8.584969534},
{"learn":[0.09392662824],"iteration":285,"passed_time":3.434022778,"remaining_time":8.573049872},
{"learn":[0.09385684121],"iteration":286,"passed_time":3.445111943,"remaining_time":8.558762423},
{"learn":[0.0937791267],"iteration":287,"passed_time":3.455769327,"remaining_time":8.543429726},
{"learn":[0.09373342694],"iteration":288,"passed_time":3.466447624,"remaining_time":8.528180833},
{"learn":[0.09364166722],"iteration":289,"passed_time":3.477599485,"remaining_time":8.514122876},
{"learn":[0.09354761227],"iteration":290,"passed_time":3.488347432,"remaining_time":8.499100788},
{"learn":[0.09349508176],"iteration":291,"passed_time":3.499518794,"remaining_time":8.485134611},
{"learn":[0.09340290976],"iteration":292,"passed_time":3.51153217,"remaining_time":8.473219264},
{"learn":[0.0933573898],"iteration":293,"passed_time":3.522193213,"remaining_time":8.458055811},
{"learn":[0.09327504862],"iteration":294,"passed_time":3.533168887,"remaining_time":8.443674798},
{"learn":[0.0932133228],"iteration":295,"passed_time":3.54392902,"remaining_time":8.428804156},
{"learn":[0.09307390118],"iteration":296,"passed_time":3.555303836,"remaining_time":8.41541615},
{"learn":[0.09299189666],"iteration":297,"passed_time":3.56632952,"remaining_time":8.401219204},
{"learn":[0.09289495533],"iteration":298,"passed_time":3.577338037,"remaining_time":8.387003224},
{"learn":[0.09280995462],"iteration":299,"passed_time":3.588810679,"remaining_time":8.373891584},
{"learn":[0.09273476669],"iteration":300,"passed_time":3.599614777,"remaining_time":8.359238304},
{"learn":[0.09264267883],"iteration":301,"passed_time":3.610989187,"remaining_time":8.345928651},
{"learn":[0.09257184554],"iteration":302,"passed_time":3.62175042,"remaining_time":8.331221264},
{"learn":[0.09251989264],"iteration":303,"passed_time":3.631913919,"remaining_time":8.315171342},
{"learn":[0.09246752477],"iteration":304,"passed_time":3.642443319,"remaining_time":8.299993791},
{"learn":[0.09239888183],"iteration":305,"passed_time":3.653693324,"remaining_time":8.286480937},
{"learn":[0.0923332736],"iteration":306,"passed_time":3.664758672,"remaining_time":8.272565993},
{"learn":[0.09227471644],"iteration":307,"passed_time":3.675797876,"remaining_time":8.258610812},
{"learn":[0.09216911495],"iteration":308,"passed_time":3.68701934,"remaining_time":8.245082084},
{"learn":[0.0920671782],"iteration":309,"passed_time":3.698149921,"remaining_time":8.231365953},
{"learn":[0.09198830207],"iteration":310,"passed_time":3.708273053,"remaining_time":8.215434512},
{"learn":[0.09190476243],"iteration":311,"passed_time":3.719668699,"remaining_time":8.202346362},
{"learn":[0.09176456733],"iteration":312,"passed_time":3.730876397,"remaining_time":8.1888565},
{"learn":[0.09169880621],"iteration":313,"passed_time":3.741897704,"remaining_time":8.174973965},
{"learn":[0.0916179322],"iteration":314,"passed_time":3.752558116,"remaining_time":8.160324791},
{"learn":[0.09152249242],"iteration":315,"passed_time":3.765484603,"remaining_time":8.150605913},
{"learn":[0.09143851773],"iteration":316,"passed_time":3.777692305,"remaining_time":8.139318121},
{"learn":[0.091304621],"iteration":317,"passed_time":3.78976043,"remaining_time":8.127725198},
{"learn":[0.09124985212],"iteration":318,"passed_time":3.801048826,"remaining_time":8.114464735},
{"learn":[0.09118375118],"iteration":319,"passed_time":3.811927375,"remaining_time":8.100345671},
{"learn":[0.09110896885],"iteration":320,"passed_time":3.822951941,"remaining_time":8.086555663},
{"learn":[0.09104877319],"iteration":321,"passed_time":3.833606752,"remaining_time":8.072004278},
{"learn":[0.09096448229],"iteration":322,"passed_time":3.845473721,"remaining_time":8.060017675},
{"learn":[0.0908901361],"iteration":323,"passed_time":3.856660149,"remaining_time":8.046611915},
{"learn":[0.0908058659],"iteration":324,"passed_time":3.867517768,"remaining_time":8.032536903},
{"learn":[0.09072899839],"iteration":325,"passed_time":3.878862477,"remaining_time":8.01948868},
{"learn":[0.09066746866],"iteration":326,"passed_time":3.889937091,"remaining_time":8.005894992},
{"learn":[0.09063392754],"iteration":327,"passed_time":3.900066199,"remaining_time":7.99037953},
{"learn":[0.09054901337],"iteration":328,"passed_time":3.911175273,"remaining_time":7.976895466},
{"learn":[0.09050500183],"iteration":329,"passed_time":3.921653552,"remaining_time":7.962145091},
{"learn":[0.0904352655],"iteration":330,"passed_time":3.93300832,"remaining_time":7.949192042},
{"learn":[0.09034153328],"iteration":331,"passed_time":3.94419297,"remaining_time":7.935906337},
{"learn":[0.09020451362],"iteration":332,"passed_time":3.955711679,"remaining_time":7.923302371},
{"learn":[0.09018629722],"iteration":333,"passed_time":3.965774293,"remaining_time":7.907801435},
{"learn":[0.09014446442],"iteration":334,"passed_time":3.976636532,"remaining_time":7.893920281},
{"learn":[0.09005049275],"iteration":335,"passed_time":3.987476128,"remaining_time":7.880012349},
{"learn":[0.08998933212],"iteration":336,"passed_time":3.998049212,"remaining_time":7.865598301},
{"learn":[0.0898751317],"iteration":337,"passed_time":4.009015749,"remaining_time":7.851977592},
{"learn":[0.08980219116],"iteration":338,"passed_time":4.020063947,"remaining_time":7.838531768},
{"learn":[0.08973819912],"iteration":339,"passed_time":4.030844094,"remaining_time":7.824579711},
{"learn":[0.08969638],"iteration":340,"passed_time":4.041803734,"remaining_time":7.810993141},
{"learn":[0.08963257847],"iteration":341,"passed_time":4.053326024,"remaining_time":7.798504456},
{"learn":[0.08954559672],"iteration":342,"passed_time":4.066714921,"remaining_time":7.789596801},
{"learn":[0.08949381728],"iteration":343,"passed_time":4.079455584,"remaining_time":7.779426928},
{"learn":[0.08945562047],"iteration":344,"passed_time":4.090810232,"remaining_time":7.76661073},
{"learn":[0.08941671646],"iteration":345,"passed_time":4.101793056,"remaining_time":7.753100169},
{"learn":[0.08930300747],"iteration":346,"passed_time":4.113315514,"remaining_time":7.740619684},
{"learn":[0.08923901863],"iteration":347,"passed_time":4.124898541,"remaining_time":7.728258187},
{"learn":[0.08921972925],"iteration":348,"passed_time":4.134450013,"remaining_time":7.712111629},
{"learn":[0.08911946075],"iteration":349,"passed_time":4.145798238,"remaining_time":7.699339585},
{"learn":[0.08906629838],"iteration":350,"passed_time":4.15619547,"remaining_time":7.684817264},
{"learn":[0.08900046645],"iteration":351,"passed_time":4.167757063,"remaining_time":7.672461866},
{"learn":[0.08890246698],"iteration":352,"passed_time":4.1793385,"remaining_time":7.660147336},
{"learn":[0.0888171052],"iteration":353,"passed_time":4.189999939,"remaining_time":7.64615808},
{"learn":[0.08865403875],"iteration":354,"passed_time":4.201525707,"remaining_time":7.633757974},
{"learn":[0.08856917534],"iteration":355,"passed_time":4.212958653,"remaining_time":7.621194867},
{"learn":[0.08850486296],"iteration":356,"passed_time":4.224209863,"remaining_time":7.608310762},
{"learn":[0.08842956336],"iteration":357,"passed_time":4.235288897,"remaining_time":7.595127016},
{"learn":[0.08837962011],"iteration":358,"passed_time":4.245893682,"remaining_time":7.581108218},
{"learn":[0.08830484451],"iteration":359,"passed_time":4.256923767,"remaining_time":7.567864475},
{"learn":[0.08827003097],"iteration":360,"passed_time":4.267083376,"remaining_time":7.553092181},
{"learn":[0.08816204385],"iteration":361,"passed_time":4.280140679,"remaining_time":7.543452356},
{"learn":[0.08807592859],"iteration":362,"passed_time":4.293228819,"remaining_time":7.533847817},
{"learn":[0.08800395539],"iteration":363,"passed_time":4.306535343,"remaining_time":7.524605709},
{"learn":[0.08794301394],"iteration":364,"passed_time":4.318872715,"remaining_time":7.513655271},
{"learn":[0.08787352948],"iteration":365,"passed_time":4.331559538,"remaining_time":7.503302588},
{"learn":[0.087675445],"iteration":366,"passed_time":4.344776676,"remaining_time":7.493851869},
{"learn":[0.08755835513],"iteration":367,"passed_time":4.357754991,"remaining_time":7.483970528},
{"learn":[0.0875123059],"iteration":368,"passed_time":4.369602431,"remaining_time":7.472138574},
{"learn":[0.08745847129],"iteration":369,"passed_time":4.381678098,"remaining_time":7.46069514},
{"learn":[0.08739076787],"iteration":370,"passed_time":4.393845462,"remaining_time":7.449403762},
{"learn":[0.08734664099],"iteration":371,"passed_time":4.406121318,"remaining_time":7.438290828},
{"learn":[0.08721539611],"iteration":372,"passed_time":4.419250633,"remaining_time":7.428606292},
{"learn":[0.08715476882],"iteration":373,"passed_time":4.43219558,"remaining_time":7.418594741},
{"learn":[0.08705587181],"iteration":374,"passed_time":4.444689017,"remaining_time":7.407815028},
{"learn":[0.08700622239],"iteration":375,"passed_time":4.457521296,"remaining_time":7.397588533},
{"learn":[0.08694794091],"iteration":376,"passed_time":4.470316638,"remaining_time":7.387287176},
{"learn":[0.08689010357],"iteration":377,"passed_time":4.483235351,"remaining_time":7.37717563},
{"learn":[0.08679738943],"iteration":378,"passed_time":4.495904491,"remaining_time":7.366640341},
{"learn":[0.08661427642],"iteration":379,"passed_time":4.508626875,"remaining_time":7.356180691},
{"learn":[0.08653917808],"iteration":380,"passed_time":4.52092316,"remaining_time":7.345016893},
{"learn":[0.08645785065],"iteration":381,"passed_time":4.533966005,"remaining_time":7.335054951},
{"learn":[0.08637779973],"iteration":382,"passed_time":4.547153542,"remaining_time":7.325310014},
{"learn":[0.08624877384],"iteration":383,"passed_time":4.560542868,"remaining_time":7.315870851},
{"learn":[0.08616888372],"iteration":384,"passed_time":4.57305559,"remaining_time":7.305010877},
{"learn":[0.086099876],"iteration":385,"passed_time":4.585823437,"remaining_time":7.294548161},
{"learn":[0.08602354987],"iteration":386,"passed_time":4.598364544,"remaining_time":7.283714382},
{"learn":[0.08598530505],"iteration":387,"passed_time":4.610699036,"remaining_time":7.272545902},
{"learn":[0.08595593675],"iteration":388,"passed_time":4.622219694,"remaining_time":7.260093143},
{"learn":[0.08591644865],"iteration":389,"passed_time":4.634490494,"remaining_time":7.248818465},
{"learn":[0.08582728559],"iteration":390,"passed_time":4.647050561,"remaining_time":7.237989237},
{"learn":[0.08573432115],"iteration":391,"passed_time":4.659261596,"remaining_time":7.226609822},
{"learn":[0.08570614393],"iteration":392,"passed_time":4.671599444,"remaining_time":7.215422042},
{"learn":[0.08566567028],"iteration":393,"passed_time":4.683456909,"remaining_time":7.203489561},
{"learn":[0.08556612],"iteration":394,"passed_time":4.696203157,"remaining_time":7.192918759},
{"learn":[0.0854878789],"iteration":395,"passed_time":4.708767688,"remaining_time":7.182059807},
{"learn":[0.08541519456],"iteration":396,"passed_time":4.721762318,"remaining_time":7.171845535},
{"learn":[0.08536105247],"iteration":397,"passed_time":4.733784439,"remaining_time":7.160146312},
{"learn":[0.08530411584],"iteration":398,"passed_time":4.74568952,"remaining_time":7.148269177},
{"learn":[0.08522727411],"iteration":399,"passed_time":4.758383559,"remaining_time":7.137575338},
{"learn":[0.0851855503],"iteration":400,"passed_time":4.770495121,"remaining_time":7.126001441},
{"learn":[0.08515955825],"iteration":401,"passed_time":4.78090609,"remaining_time":7.111895129},
{"learn":[0.08507533814],"iteration":402,"passed_time":4.79155723,"remaining_time":7.098162943},
{"learn":[0.08495817346],"iteration":403,"passed_time":4.803175374,"remaining_time":7.085872582},
{"learn":[0.08492388759],"iteration":404,"passed_time":4.813665011,"remaining_time":7.071927608},
{"learn":[0.08480979231],"iteration":405,"passed_time":4.825305529,"remaining_time":7.059683459},
{"learn":[0.08479647774],"iteration":406,"passed_time":4.834863446,"remaining_time":7.044407921},
{"learn":[0.0847132506],"iteration":407,"passed_time":4.845888433,"remaining_time":7.031289099},
{"learn":[0.08465429445],"iteration":408,"passed_time":4.857096198,"remaining_time":7.018444628},
{"learn":[0.08458250806],"iteration":409,"passed_time":4.868088208,"remaining_time":7.005297665},
{"learn":[0.08451014856],"iteration":410,"passed_time":4.879030858,"remaining_time":6.992090451},
{"learn":[0.08445548607],"iteration":411,"passed_time":4.889591606,"remaining_time":6.978349186},
{"learn":[0.08434740938],"iteration":412,"passed_time":4.901230112,"remaining_time":6.966155147},
{"learn":[0.08428324571],"iteration":413,"passed_time":4.912893621,"remaining_time":6.953999184},
{"learn":[0.08423392558],"iteration":414,"passed_time":4.923636916,"remaining_time":6.940548423},
{"learn":[0.08412220456],"iteration":415,"passed_time":4.935238034,"remaining_time":6.928314933},
{"learn":[0.08407420499],"iteration":416,"passed_time":4.945974895,"remaining_time":6.914876173},
{"learn":[0.08400640804],"iteration":417,"passed_time":4.957381787,"remaining_time":6.902383254},
{"learn":[0.08397815892],"iteration":418,"passed_time":4.967915891,"remaining_time":6.888685281},
{"learn":[0.08385651217],"iteration":419,"passed_time":4.979223349,"remaining_time":6.876070339},
{"learn":[0.08382400482],"iteration":420,"passed_time":4.989436994,"remaining_time":6.861957291},
{"learn":[0.08378487728],"iteration":421,"passed_time":4.999859577,"remaining_time":6.848148899},
{"learn":[0.08370393194],"iteration":422,"passed_time":5.011436484,"remaining_time":6.835931091},
{"learn":[0.08360208634],"iteration":423,"passed_time":5.022628335,"remaining_time":6.82319321},
{"learn":[0.08357339356],"iteration":424,"passed_time":5.033566994,"remaining_time":6.81012005},
{"learn":[0.08352149243],"iteration":425,"passed_time":5.044591739,"remaining_time":6.797172906},
{"learn":[0.08345368635],"iteration":426,"passed_time":5.055229362,"remaining_time":6.783715279},
{"learn":[0.0834473952],"iteration":427,"passed_time":5.065321525,"remaining_time":6.769541852},
{"learn":[0.08342289027],"iteration":428,"passed_time":5.076924499,"remaining_time":6.757398342},
{"learn":[0.08339351695],"iteration":429,"passed_time":5.089777653,"remaining_time":6.746914563},
{"learn":[0.08328239444],"iteration":430,"passed_time":5.106700202,"remaining_time":6.741792146},
{"learn":[0.08325732788],"iteration":431,"passed_time":5.119331771,"remaining_time":6.730973254},
{"learn":[0.08320977632],"iteration":432,"passed_time":5.132128791,"remaining_time":6.720362644},
{"learn":[0.08317267975],"iteration":433,"passed_time":5.144816805,"remaining_time":6.709599796},
{"learn":[0.08314073964],"iteration":434,"passed_time":5.156983341,"remaining_time":6.698150776},
{"learn":[0.08312520639],"iteration":435,"passed_time":5.168614584,"remaining_time":6.686006022},
{"learn":[0.0830319302],"iteration":436,"passed_time":5.181474299,"remaining_time":6.675446293},
{"learn":[0.08298790161],"iteration":437,"passed_time":5.193775698,"remaining_time":6.664159686},
{"learn":[0.0828628481],"iteration":438,"passed_time":5.206046441,"remaining_time":6.652829279},
{"learn":[0.08279905224],"iteration":439,"passed_time":5.21824747,"remaining_time":6.641405871},
{"learn":[0.08276320947],"iteration":440,"passed_time":5.230395191,"remaining_time":6.629911364},
{"learn":[0.08274056687],"iteration":441,"passed_time":5.242029167,"remaining_time":6.617765329},
{"learn":[0.08267156049],"iteration":442,"passed_time":5.254580316,"remaining_time":6.6067748},
{"learn":[0.08260410634],"iteration":443,"passed_time":5.267107862,"remaining_time":6.595747683},
{"learn":[0.08252120578],"iteration":444,"passed_time":5.279507409,"remaining_time":6.584554184},
{"learn":[0.0824889178],"iteration":445,"passed_time":5.29156828,"remaining_time":6.57293459},
{"learn":[0.08241910984],"iteration":446,"passed_time":5.304583325,"remaining_time":6.562493465},
{"learn":[0.08236392712],"iteration":447,"passed_time":5.317133963,"remaining_time":6.551468633},
{"learn":[0.08228753706],"iteration":448,"passed_time":5.329942674,"remaining_time":6.540753705},
{"learn":[0.08224050485],"iteration":449,"passed_time":5.342773307,"remaining_time":6.530056264},
{"learn":[0.08221036388],"iteration":450,"passed_time":5.354475162,"remaining_time":6.517975308},
{"learn":[0.08215650763],"iteration":451,"passed_time":5.367276029,"remaining_time":6.50722846},
{"learn":[0.08207718559],"iteration":452,"passed_time":5.379985353,"remaining_time":6.496362005},
{"learn":[0.08203058292],"iteration":453,"passed_time":5.392418063,"remaining_time":6.485154763},
{"learn":[0.08200210239],"iteration":454,"passed_time":5.404246743,"remaining_time":6.473218626},
{"learn":[0.08195148589],"iteration":455,"passed_time":5.416156865,"remaining_time":6.461380119},
{"learn":[0.08186211248],"iteration":456,"passed_time":5.429548565,"remaining_time":6.451301687},
{"learn":[0.08182106486],"iteration":457,"passed_time":5.441715339,"remaining_time":6.439759201},
{"learn":[0.08172473632],"iteration":458,"passed_time":5.455501795,"remaining_time":6.43012303},
{"learn":[0.08167158957],"iteration":459,"passed_time":5.467471839,"remaining_time":6.418336507},
{"learn":[0.08162090794],"iteration":460,"passed_time":5.480300712,"remaining_time":6.407553327},
{"learn":[0.08155172414],"iteration":461,"passed_time":5.4925037,"remaining_time":6.396032448},
{"learn":[0.08147645128],"iteration":462,"passed_time":5.505113898,"remaining_time":6.384980914},
{"learn":[0.08142099949],"iteration":463,"passed_time":5.518083841,"remaining_time":6.37433823},
{"learn":[0.08133677827],"iteration":464,"passed_time":5.531624731,"remaining_time":6.364342433},
{"learn":[0.08122240671],"iteration":465,"passed_time":5.544240329,"remaining_time":6.353271106},
{"learn":[0.08119219376],"iteration":466,"passed_time":5.555730395,"remaining_time":6.340908567},
{"learn":[0.08115125014],"iteration":467,"passed_time":5.568454607,"remaining_time":6.329952673},
{"learn":[0.08110286468],"iteration":468,"passed_time":5.581062751,"remaining_time":6.318857827},
{"learn":[0.08106338797],"iteration":469,"passed_time":5.59376107,"remaining_time":6.307858228},
{"learn":[0.08103932209],"iteration":470,"passed_time":5.606062593,"remaining_time":6.296405758},
{"learn":[0.08100756637],"iteration":471,"passed_time":5.618094467,"remaining_time":6.284648048},
{"learn":[0.0809628098],"iteration":472,"passed_time":5.630596991,"remaining_time":6.273413561},
{"learn":[0.08090916325],"iteration":473,"passed_time":5.643563052,"remaining_time":6.262688112},
{"learn":[0.08085520306],"iteration":474,"passed_time":5.656384251,"remaining_time":6.25179312},
{"learn":[0.08082711862],"iteration":475,"passed_time":5.669105545,"remaining_time":6.240780054},
{"learn":[0.08077875159],"iteration":476,"passed_time":5.682144605,"remaining_time":6.230108235},
{"learn":[0.08073917965],"iteration":477,"passed_time":5.69395827,"remaining_time":6.21808832},
{"learn":[0.08072223068],"iteration":478,"passed_time":5.705250802,"remaining_time":6.205502438},
{"learn":[0.08067098676],"iteration":479,"passed_time":5.717867176,"remaining_time":6.194356107},
{"learn":[0.08061610348],"iteration":480,"passed_time":5.730837381,"remaining_time":6.183585449},
{"learn":[0.08052955498],"iteration":481,"passed_time":5.743950988,"remaining_time":6.172959776},
{"learn":[0.08047267055],"iteration":482,"passed_time":5.757163036,"remaining_time":6.162429171},
{"learn":[0.08041280096],"iteration":483,"passed_time":5.770832057,"remaining_time":6.152374672},
{"learn":[0.08034315927],"iteration":484,"passed_time":5.784200175,"remaining_time":6.141985753},
{"learn":[0.08028741527],"iteration":485,"passed_time":5.797476892,"remaining_time":6.131487906},
{"learn":[0.08024228856],"iteration":486,"passed_time":5.811391842,"remaining_time":6.121650955},
{"learn":[0.08019351334],"iteration":487,"passed_time":5.824851377,"remaining_time":6.111319477},
{"learn":[0.08012479388],"iteration":488,"passed_time":5.838590028,"remaining_time":6.101266879},
{"learn":[0.08006985705],"iteration":489,"passed_time":5.85155966,"remaining_time":6.09039883},
{"learn":[0.08000049218],"iteration":490,"passed_time":5.864879401,"remaining_time":6.079885164},
{"learn":[0.07992482521],"iteration":491,"passed_time":5.878469195,"remaining_time":6.069638925},
{"learn":[0.07985914579],"iteration":492,"passed_time":5.891805299,"remaining_time":6.059118228},
{"learn":[0.07978348268],"iteration":493,"passed_time":5.90471031,"remaining_time":6.048144568},
{"learn":[0.07975132166],"iteration":494,"passed_time":5.916793244,"remaining_time":6.03632442},
{"learn":[0.0796748058],"iteration":495,"passed_time":5.929518241,"remaining_time":6.025155632},
{"learn":[0.07961304834],"iteration":496,"passed_time":5.943346576,"remaining_time":6.015097239},
{"learn":[0.07956549428],"iteration":497,"passed_time":5.956287982,"remaining_time":6.004129653},
{"learn":[0.07948906773],"iteration":498,"passed_time":5.969039325,"remaining_time":5.992963331},
{"learn":[0.0794612001],"iteration":499,"passed_time":5.980546938,"remaining_time":5.980546938},
{"learn":[0.0793660529],"iteration":500,"passed_time":5.993282245,"remaining_time":5.969356966},
{"learn":[0.07932021946],"iteration":501,"passed_time":6.005484724,"remaining_time":5.957632256},
{"learn":[0.07926418265],"iteration":502,"passed_time":6.018997219,"remaining_time":5.947200036},
{"learn":[0.07921959959],"iteration":503,"passed_time":6.031693053,"remaining_time":5.935951894},
{"learn":[0.0791558455],"iteration":504,"passed_time":6.044359576,"remaining_time":5.924669287},
{"learn":[0.07909759521],"iteration":505,"passed_time":6.056825604,"remaining_time":5.913185471},
{"learn":[0.07904994207],"iteration":506,"passed_time":6.068612814,"remaining_time":5.901037706},
{"learn":[0.07903670401],"iteration":507,"passed_time":6.080796756,"remaining_time":5.889275598},
{"learn":[0.07898964907],"iteration":508,"passed_time":6.095498117,"remaining_time":5.879940227},
{"learn":[0.07892911373],"iteration":509,"passed_time":6.108545925,"remaining_time":5.868995104},
{"learn":[0.07887682398],"iteration":510,"passed_time":6.120962361,"remaining_time":5.857437563},
{"learn":[0.07882338219],"iteration":511,"passed_time":6.133521335,"remaining_time":5.846012522},
{"learn":[0.0787804258],"iteration":512,"passed_time":6.146572114,"remaining_time":5.835049941},
{"learn":[0.07873530494],"iteration":513,"passed_time":6.158833516,"remaining_time":5.823332858},
{"learn":[0.07867152017],"iteration":514,"passed_time":6.17252294,"remaining_time":5.812958497},
{"learn":[0.07857319805],"iteration":515,"passed_time":6.18541559,"remaining_time":5.801823926},
{"learn":[0.07854794508],"iteration":516,"passed_time":6.197206491,"remaining_time":5.78965326},
{"learn":[0.07850985542],"iteration":517,"passed_time":6.209670627,"remaining_time":5.778110506},
{"learn":[0.07849311195],"iteration":518,"passed_time":6.221577805,"remaining_time":5.766048024},
{"learn":[0.07845498354],"iteration":519,"passed_time":6.233396766,"remaining_time":5.753904707},
{"learn":[0.07839777217],"iteration":520,"passed_time":6.245833484,"remaining_time":5.742330593},
{"learn":[0.07836717092],"iteration":521,"passed_time":6.256769106,"remaining_time":5.729378607},
{"learn":[0.07829493809],"iteration":522,"passed_time":6.26822032,"remaining_time":5.716904575},
{"learn":[0.07825068992],"iteration":523,"passed_time":6.279907589,"remaining_time":5.704648878},
{"learn":[0.07821839798],"iteration":524,"passed_time":6.290978637,"remaining_time":5.691837815},
{"learn":[0.07818158005],"iteration":525,"passed_time":6.301795904,"remaining_time":5.678804674},
{"learn":[0.07812593451],"iteration":526,"passed_time":6.3124475,"remaining_time":5.665631248},
{"learn":[0.0780150833],"iteration":527,"passed_time":6.32395624,"remaining_time":5.653233609},
{"learn":[0.07795844678],"iteration":528,"passed_time":6.335665244,"remaining_time":5.641017637},
{"learn":[0.07790677654],"iteration":529,"passed_time":6.347276889,"remaining_time":5.628717241},
{"learn":[0.07788089141],"iteration":530,"passed_time":6.357865902,"remaining_time":5.615516211},
{"learn":[0.07785989454],"iteration":531,"passed_time":6.368103034,"remaining_time":5.602015451},
{"learn":[0.07782273997],"iteration":532,"passed_time":6.378789925,"remaining_time":5.588921004},
{"learn":[0.07779075031],"iteration":533,"passed_time":6.389177942,"remaining_time":5.575574759},
{"learn":[0.07772337733],"iteration":534,"passed_time":6.400667432,"remaining_time":5.563196927},
{"learn":[0.07768214644],"iteration":535,"passed_time":6.412297176,"remaining_time":5.550943824},
{"learn":[0.07766713513],"iteration":536,"passed_time":6.422378574,"remaining_time":5.537358063},
{"learn":[0.07758903326],"iteration":537,"passed_time":6.433286823,"remaining_time":5.524495376},
{"learn":[0.07756695202],"iteration":538,"passed_time":6.444032175,"remaining_time":5.511500618},
{"learn":[0.07750308888],"iteration":539,"passed_time":6.455309425,"remaining_time":5.498967288},
{"learn":[0.07745849927],"iteration":540,"passed_time":6.466321262,"remaining_time":5.486213419},
{"learn":[0.07743535754],"iteration":541,"passed_time":6.476538763,"remaining_time":5.472794748},
{"learn":[0.07738806958],"iteration":542,"passed_time":6.487629787,"remaining_time":5.460123044},
{"learn":[0.0773615153],"iteration":543,"passed_time":6.498419591,"remaining_time":5.447204657},
{"learn":[0.07733252223],"iteration":544,"passed_time":6.509434917,"remaining_time":5.434482362},
{"learn":[0.07730309242],"iteration":545,"passed_time":6.519653535,"remaining_time":5.421103855},
{"learn":[0.07724974839],"iteration":546,"passed_time":6.531085686,"remaining_time":5.408741894},
{"learn":[0.0772052207],"iteration":547,"passed_time":6.541605061,"remaining_time":5.395630452},
{"learn":[0.07718501206],"iteration":548,"passed_time":6.552090996,"remaining_time":5.382500982},
{"learn":[0.07715235669],"iteration":549,"passed_time":6.562528919,"remaining_time":5.369341843},
{"learn":[0.0771078609],"iteration":550,"passed_time":6.573498324,"remaining_time":5.356625676},
{"learn":[0.07706911146],"iteration":551,"passed_time":6.584744897,"remaining_time":5.344140786},
{"learn":[0.07704756003],"iteration":552,"passed_time":6.59484463,"remaining_time":5.330733363},
{"learn":[0.077014038],"iteration":553,"passed_time":6.605894324,"remaining_time":5.318102651},
{"learn":[0.07695637025],"iteration":554,"passed_time":6.617104123,"remaining_time":5.305606008},
{"learn":[0.07689692275],"iteration":555,"passed_time":6.628131917,"remaining_time":5.292968653},
{"learn":[0.07683081763],"iteration":556,"passed_time":6.639353223,"remaining_time":5.280490983},
{"learn":[0.07679407296],"iteration":557,"passed_time":6.650227376,"remaining_time":5.267742832},
{"learn":[0.07675906598],"iteration":558,"passed_time":6.660880236,"remaining_time":5.254826805},
{"learn":[0.07672230439],"iteration":559,"passed_time":6.671565041,"remaining_time":5.241943961},
{"learn":[0.07667934058],"iteration":560,"passed_time":6.682775368,"remaining_time":5.22948019},
{"learn":[0.07664239579],"iteration":561,"passed_time":6.693749109,"remaining_time":5.216836494},
{"learn":[0.07662170013],"iteration":562,"passed_time":6.703907667,"remaining_time":5.203565987},
{"learn":[0.07654938022],"iteration":563,"passed_time":6.71524825,"remaining_time":5.191220279},
{"learn":[0.076534365],"iteration":564,"passed_time":6.725875937,"remaining_time":5.178329261},
{"learn":[0.07650371726],"iteration":565,"passed_time":6.738344103,"remaining_time":5.166857492},
{"learn":[0.07646814915],"iteration":566,"passed_time":6.751125256,"remaining_time":5.155621228},
{"learn":[0.07645193244],"iteration":567,"passed_time":6.762737307,"remaining_time":5.143490346},
{"learn":[0.0764148529],"iteration":568,"passed_time":6.774706625,"remaining_time":5.131631908},
{"learn":[0.07638505795],"iteration":569,"passed_time":6.78614455,"remaining_time":5.119372204},
{"learn":[0.07634122646],"iteration":570,"passed_time":6.797756617,"remaining_time":5.107246215},
{"learn":[0.07628583124],"iteration":571,"passed_time":6.81014784,"remaining_time":5.095705027},
{"learn":[0.07624288355],"iteration":572,"passed_time":6.821289783,"remaining_time":5.083229908},
{"learn":[0.07620540643],"iteration":573,"passed_time":6.833612935,"remaining_time":5.07163608},
{"learn":[0.07618384171],"iteration":574,"passed_time":6.8440772,"remaining_time":5.058665757},
{"learn":[0.0761245824],"iteration":575,"passed_time":6.855825813,"remaining_time":5.046649557},
{"learn":[0.07608773673],"iteration":576,"passed_time":6.866437313,"remaining_time":5.033800664},
{"learn":[0.07607753823],"iteration":577,"passed_time":6.875932493,"remaining_time":5.020144484},
{"learn":[0.07604008871],"iteration":578,"passed_time":6.886849701,"remaining_time":5.007536656},
{"learn":[0.07603086095],"iteration":579,"passed_time":6.896842813,"remaining_time":4.994265485},
{"learn":[0.07594079087],"iteration":580,"passed_time":6.90832288,"remaining_time":4.982077946},
{"learn":[0.07588729185],"iteration":581,"passed_time":6.919087204,"remaining_time":4.969378782},
{"learn":[0.07585960912],"iteration":582,"passed_time":6.93030006,"remaining_time":4.957007075},
{"learn":[0.0758161818],"iteration":583,"passed_time":6.941500428,"remaining_time":4.944630442},
{"learn":[0.07576381942],"iteration":584,"passed_time":6.952749271,"remaining_time":4.932292218},
{"learn":[0.07572915534],"iteration":585,"passed_time":6.964076914,"remaining_time":4.920013383},
{"learn":[0.07569598409],"iteration":586,"passed_time":6.974504735,"remaining_time":4.907104694},
{"learn":[0.0756422176],"iteration":587,"passed_time":6.985423281,"remaining_time":4.894548285},
{"learn":[0.07561017932],"iteration":588,"passed_time":6.995597327,"remaining_time":4.881477931},
{"learn":[0.07555599771],"iteration":589,"passed_time":7.006793412,"remaining_time":4.869127625},
{"learn":[0.07553102376],"iteration":590,"passed_time":7.017714165,"remaining_time":4.856590683},
{"learn":[0.07550271261],"iteration":591,"passed_time":7.027969932,"remaining_time":4.843600899},
{"learn":[0.0754303203],"iteration":592,"passed_time":7.03894942,"remaining_time":4.831117056},
{"learn":[0.07533875802],"iteration":593,"passed_time":7.049993979,"remaining_time":4.818682753},
{"learn":[0.07530295429],"iteration":594,"passed_time":7.06142307,"remaining_time":4.806514863},
{"learn":[0.07525939055],"iteration":595,"passed_time":7.075314236,"remaining_time":4.796018375},
{"learn":[0.07518814213],"iteration":596,"passed_time":7.089892393,"remaining_time":4.785974262},
{"learn":[0.07515092568],"iteration":597,"passed_time":7.100752223,"remaining_time":4.773415374},
{"learn":[0.07510046752],"iteration":598,"passed_time":7.112507868,"remaining_time":4.761461862},
{"learn":[0.07499157527],"iteration":599,"passed_time":7.123629347,"remaining_time":4.749086232},
{"learn":[0.07492628614],"iteration":600,"passed_time":7.135515005,"remaining_time":4.737222108},
{"learn":[0.07488780166],"iteration":601,"passed_time":7.14647118,"remaining_time":4.724743405},
{"learn":[0.07478033891],"iteration":602,"passed_time":7.157024975,"remaining_time":4.712004834},
{"learn":[0.07470563227],"iteration":603,"passed_time":7.168257983,"remaining_time":4.69971881},
{"learn":[0.0746547477],"iteration":604,"passed_time":7.180301889,"remaining_time":4.687965696},
{"learn":[0.07459635411],"iteration":605,"passed_time":7.191473764,"remaining_time":4.675644658},
{"learn":[0.07452493255],"iteration":606,"passed_time":7.202818276,"remaining_time":4.66343918},
{"learn":[0.07447673886],"iteration":607,"passed_time":7.213951387,"remaining_time":4.651100237},
{"learn":[0.07443186919],"iteration":608,"passed_time":7.225449204,"remaining_time":4.638999407},
{"learn":[0.07437876404],"iteration":609,"passed_time":7.237748331,"remaining_time":4.627412867},
{"learn":[0.07434994143],"iteration":610,"passed_time":7.24940157,"remaining_time":4.615412784},
{"learn":[0.07430609875],"iteration":611,"passed_time":7.260519428,"remaining_time":4.603074409},
{"learn":[0.07425806648],"iteration":612,"passed_time":7.271328283,"remaining_time":4.590544936},
{"learn":[0.07422468863],"iteration":613,"passed_time":7.282410698,"remaining_time":4.578193045},
{"learn":[0.07418769941],"iteration":614,"passed_time":7.29318207,"remaining_time":4.565650564},
{"learn":[0.07415788111],"iteration":615,"passed_time":7.304042491,"remaining_time":4.553169345},
{"learn":[0.07412943591],"iteration":616,"passed_time":7.315025046,"remaining_time":4.540769194},
{"learn":[0.07410214567],"iteration":617,"passed_time":7.32591743,"remaining_time":4.528317893},
{"learn":[0.07409404477],"iteration":618,"passed_time":7.336504164,"remaining_time":4.5156835},
{"learn":[0.07403765578],"iteration":619,"passed_time":7.347856559,"remaining_time":4.503524988},
{"learn":[0.07400567093],"iteration":620,"passed_time":7.358433394,"remaining_time":4.490895743},
{"learn":[0.0739785005],"iteration":621,"passed_time":7.368916493,"remaining_time":4.478216132},
{"learn":[0.07391494074],"iteration":622,"passed_time":7.379688001,"remaining_time":4.4657181},
{"learn":[0.07384863894],"iteration":623,"passed_time":7.391003289,"remaining_time":4.453553264},
{"learn":[0.07379591941],"iteration":624,"passed_time":7.402065906,"remaining_time":4.441239543},
{"learn":[0.07376588789],"iteration":625,"passed_time":7.412173895,"remaining_time":4.428359484},
{"learn":[0.07372863411],"iteration":626,"passed_time":7.423618466,"remaining_time":4.416283393},
{"learn":[0.07368339561],"iteration":627,"passed_time":7.434678527,"remaining_time":4.403981548},
{"learn":[0.0736504093],"iteration":628,"passed_time":7.445596531,"remaining_time":4.391599862},
{"learn":[0.07361342567],"iteration":629,"passed_time":7.456435074,"remaining_time":4.379176155},
{"learn":[0.073583394],"iteration":630,"passed_time":7.466965238,"remaining_time":4.366577136},
{"learn":[0.07354167447],"iteration":631,"passed_time":7.478264848,"remaining_time":4.354432696},
{"learn":[0.07350290088],"iteration":632,"passed_time":7.489410505,"remaining_time":4.342201667},
{"learn":[0.07344797995],"iteration":633,"passed_time":7.501011513,"remaining_time":4.33023693},
{"learn":[0.07334803582],"iteration":634,"passed_time":7.512972331,"remaining_time":4.318480159},
{"learn":[0.07330851972],"iteration":635,"passed_time":7.524413999,"remaining_time":4.306425622},
{"learn":[0.07325780464],"iteration":636,"passed_time":7.535658901,"remaining_time":4.294260881},
{"learn":[0.07321116628],"iteration":637,"passed_time":7.546665929,"remaining_time":4.281964054},
{"learn":[0.07314898562],"iteration":638,"passed_time":7.557692798,"remaining_time":4.269682473},
{"learn":[0.07312074189],"iteration":639,"passed_time":7.568219213,"remaining_time":4.257123307},
{"learn":[0.07302792501],"iteration":640,"passed_time":7.578833219,"remaining_time":4.244619541},
{"learn":[0.0729822462],"iteration":641,"passed_time":7.590406155,"remaining_time":4.232656391},
{"learn":[0.0729325106],"iteration":642,"passed_time":7.601057801,"remaining_time":4.220182947},
{"learn":[0.07292457314],"iteration":643,"passed_time":7.611041244,"remaining_time":4.207345781},
{"learn":[0.07288954898],"iteration":644,"passed_time":7.621774222,"remaining_time":4.194929998},
{"learn":[0.07283393719],"iteration":645,"passed_time":7.63279698,"remaining_time":4.182678221},
{"learn":[0.07278918581],"iteration":646,"passed_time":7.644538982,"remaining_time":4.17082266},
{"learn":[0.07275378244],"iteration":647,"passed_time":7.65573169,"remaining_time":4.158669066},
{"learn":[0.07270471867],"iteration":648,"passed_time":7.667102728,"remaining_time":4.146614881},
{"learn":[0.07268018007],"iteration":649,"passed_time":7.677484608,"remaining_time":4.134030174},
{"learn":[0.07263775204],"iteration":650,"passed_time":7.688115949,"remaining_time":4.12158597},
{"learn":[0.07261440344],"iteration":651,"passed_time":7.698700889,"remaining_time":4.109122561},
{"learn":[0.07258533715],"iteration":652,"passed_time":7.70905633,"remaining_time":4.09654295},
{"learn":[0.07254745234],"iteration":653,"passed_time":7.720698314,"remaining_time":4.08465079},
{"learn":[0.07253179899],"iteration":654,"passed_time":7.732347712,"remaining_time":4.072763299},
{"learn":[0.07248090979],"iteration":655,"passed_time":7.744893496,"remaining_time":4.06134659},
{"learn":[0.07238143878],"iteration":656,"passed_time":7.756548694,"remaining_time":4.049461495},
{"learn":[0.0723529813],"iteration":657,"passed_time":7.7677132,"remaining_time":4.037322058},
{"learn":[0.07230799191],"iteration":658,"passed_time":7.779894778,"remaining_time":4.025711865},
{"learn":[0.07225610369],"iteration":659,"passed_time":7.790910646,"remaining_time":4.013499424},
{"learn":[0.07220407179],"iteration":660,"passed_time":7.802491069,"remaining_time":4.00158014},
{"learn":[0.07212208124],"iteration":661,"passed_time":7.81354912,"remaining_time":3.98939517},
{"learn":[0.07209057663],"iteration":662,"passed_time":7.824404209,"remaining_time":3.977110435},
{"learn":[0.07206718906],"iteration":663,"passed_time":7.83467908,"remaining_time":3.964536402},
{"learn":[0.07203074116],"iteration":664,"passed_time":7.846142998,"remaining_time":3.952568277},
{"learn":[0.07196320642],"iteration":665,"passed_time":7.856895492,"remaining_time":3.940244887},
{"learn":[0.07194753438],"iteration":666,"passed_time":7.867596628,"remaining_time":3.927900565},
{"learn":[0.07187519748],"iteration":667,"passed_time":7.87898835,"remaining_time":3.91590439},
{"learn":[0.07178898137],"iteration":668,"passed_time":7.890652006,"remaining_time":3.904044565},
{"learn":[0.07174118224],"iteration":669,"passed_time":7.90207254,"remaining_time":3.892065579},
{"learn":[0.07166144802],"iteration":670,"passed_time":7.913158948,"remaining_time":3.879924432},
{"learn":[0.07165041423],"iteration":671,"passed_time":7.923500775,"remaining_time":3.867422997},
{"learn":[0.07160708552],"iteration":672,"passed_time":7.935519551,"remaining_time":3.855742783},
{"learn":[0.07155986013],"iteration":673,"passed_time":7.946764448,"remaining_time":3.843687255},
{"learn":[0.07152175384],"iteration":674,"passed_time":7.958406926,"remaining_time":3.831825557},
{"learn":[0.07149160366],"iteration":675,"passed_time":7.968722918,"remaining_time":3.819328736},
{"learn":[0.07143139611],"iteration":676,"passed_time":7.980003491,"remaining_time":3.807298564},
{"learn":[0.07135725341],"iteration":677,"passed_time":7.991389462,"remaining_time":3.795320659},
{"learn":[0.07131243277],"iteration":678,"passed_time":8.001764641,"remaining_time":3.782866642},
{"learn":[0.07129783697],"iteration":679,"passed_time":8.011845432,"remaining_time":3.770280203},
{"learn":[0.07124960831],"iteration":680,"passed_time":8.022803991,"remaining_time":3.758112296},
{"learn":[0.07122186024],"iteration":681,"passed_time":8.034089067,"remaining_time":3.746100181},
{"learn":[0.07119558716],"iteration":682,"passed_time":8.045530476,"remaining_time":3.734162754},
{"learn":[0.07117366717],"iteration":683,"passed_time":8.056123924,"remaining_time":3.721835029},
{"learn":[0.07112315828],"iteration":684,"passed_time":8.06819626,"remaining_time":3.710192441},
{"learn":[0.07107297833],"iteration":685,"passed_time":8.082677353,"remaining_time":3.69965115},
{"learn":[0.07101739444],"iteration":686,"passed_time":8.095462873,"remaining_time":3.688325879},
{"learn":[0.07097113406],"iteration":687,"passed_time":8.107556108,"remaining_time":3.676682421},
{"learn":[0.07093516852],"iteration":688,"passed_time":8.118937526,"remaining_time":3.664716358},
{"learn":[0.07088991126],"iteration":689,"passed_time":8.129962174,"remaining_time":3.652591701},
{"learn":[0.0708647949],"iteration":690,"passed_time":8.140001044,"remaining_time":3.64002941},
{"learn":[0.07083155218],"iteration":691,"passed_time":8.151094988,"remaining_time":3.627944012},
{"learn":[0.07077198442],"iteration":692,"passed_time":8.163150471,"remaining_time":3.616287438},
{"learn":[0.07076272831],"iteration":693,"passed_time":8.173186252,"remaining_time":3.603739183},
{"learn":[0.07072160097],"iteration":694,"passed_time":8.184668276,"remaining_time":3.59183284},
{"learn":[0.07070557265],"iteration":695,"passed_time":8.194919003,"remaining_time":3.579389909},
{"learn":[0.07066019606],"iteration":696,"passed_time":8.20602893,"remaining_time":3.56732678},
{"learn":[0.07063324134],"iteration":697,"passed_time":8.216583728,"remaining_time":3.555026198},
{"learn":[0.07060338887],"iteration":698,"passed_time":8.227318923,"remaining_time":3.542808291},
{"learn":[0.0705950171],"iteration":699,"passed_time":8.237787858,"remaining_time":3.53048051},
{"learn":[0.07054293639],"iteration":700,"passed_time":8.249457633,"remaining_time":3.518670232},
{"learn":[0.07050381513],"iteration":701,"passed_time":8.260435379,"remaining_time":3.506566585},
{"learn":[0.07045420719],"iteration":702,"passed_time":8.271097351,"remaining_time":3.494332736},
{"learn":[0.07040867629],"iteration":703,"passed_time":8.282368441,"remaining_time":3.482359458},
{"learn":[0.0703792],"iteration":704,"passed_time":8.292806644,"remaining_time":3.470039659},
{"learn":[0.07036092213],"iteration":705,"passed_time":8.303391673,"remaining_time":3.457786334},
{"learn":[0.07032264281],"iteration":706,"passed_time":8.31517314,"remaining_time":3.446033564},
{"learn":[0.07029094285],"iteration":707,"passed_time":8.32645968,"remaining_time":3.434076591},
{"learn":[0.07025192472],"iteration":708,"passed_time":8.337336183,"remaining_time":3.421953215},
{"learn":[0.07021589224],"iteration":709,"passed_time":8.348169084,"remaining_time":3.409815542},
{"learn":[0.07014876438],"iteration":710,"passed_time":8.358837788,"remaining_time":3.397614797},
{"learn":[0.07011225085],"iteration":711,"passed_time":8.370056541,"remaining_time":3.385640848},
{"learn":[0.07004609984],"iteration":712,"passed_time":8.381068757,"remaining_time":3.373585881},
{"learn":[0.0699980852],"iteration":713,"passed_time":8.392038543,"remaining_time":3.361516839},
{"learn":[0.06992435905],"iteration":714,"passed_time":8.403708708,"remaining_time":3.349730044},
{"learn":[0.06988754296],"iteration":715,"passed_time":8.41530502,"remaining_time":3.337914282},
{"learn":[0.06985067902],"iteration":716,"passed_time":8.4264281,"remaining_time":3.325912346},
{"learn":[0.0698240509],"iteration":717,"passed_time":8.437334317,"remaining_time":3.313827684},
{"learn":[0.06981743093],"iteration":718,"passed_time":8.446456344,"remaining_time":3.301049002},
{"learn":[0.0697903901],"iteration":719,"passed_time":8.457366372,"remaining_time":3.288975812},
{"learn":[0.06973382593],"iteration":720,"passed_time":8.468822961,"remaining_time":3.277117346},
{"learn":[0.06967091354],"iteration":721,"passed_time":8.48014433,"remaining_time":3.265207928},
{"learn":[0.0696503409],"iteration":722,"passed_time":8.491141257,"remaining_time":3.253175834},
{"learn":[0.06960273572],"iteration":723,"passed_time":8.502384619,"remaining_time":3.241240545},
{"learn":[0.06955515155],"iteration":724,"passed_time":8.513801494,"remaining_time":3.229372981},
{"learn":[0.06950200791],"iteration":725,"passed_time":8.525306461,"remaining_time":3.217539904},
{"learn":[0.06947953704],"iteration":726,"passed_time":8.535860022,"remaining_time":3.205350462},
{"learn":[0.0694478485],"iteration":727,"passed_time":8.546480722,"remaining_time":3.1931906},
{"learn":[0.06941604337],"iteration":728,"passed_time":8.557367574,"remaining_time":3.181133899},
{"learn":[0.06934351187],"iteration":729,"passed_time":8.568616179,"remaining_time":3.169214203},
{"learn":[0.06930140727],"iteration":730,"passed_time":8.579339586,"remaining_time":3.157103076},
{"learn":[0.06927206063],"iteration":731,"passed_time":8.590271054,"remaining_time":3.145071916},
{"learn":[0.06923560776],"iteration":732,"passed_time":8.601625976,"remaining_time":3.133198002},
{"learn":[0.0692278152],"iteration":733,"passed_time":8.611655058,"remaining_time":3.120845021},
{"learn":[0.06919192601],"iteration":734,"passed_time":8.6231038,"remaining_time":3.109010214},
{"learn":[0.06914863259],"iteration":735,"passed_time":8.634173934,"remaining_time":3.09704065},
{"learn":[0.06910477311],"iteration":736,"passed_time":8.645856707,"remaining_time":3.085292149},
{"learn":[0.06903873116],"iteration":737,"passed_time":8.657157312,"remaining_time":3.073408151},
{"learn":[0.06900811438],"iteration":738,"passed_time":8.667883024,"remaining_time":3.061322692},
{"learn":[0.06899339854],"iteration":739,"passed_time":8.678143198,"remaining_time":3.04907734},
{"learn":[0.06892486451],"iteration":740,"passed_time":8.690003736,"remaining_time":3.037396717},
{"learn":[0.06888093976],"iteration":741,"passed_time":8.700963806,"remaining_time":3.025402509},
{"learn":[0.06885912232],"iteration":742,"passed_time":8.711664575,"remaining_time":3.013321394},
{"learn":[0.06878827913],"iteration":743,"passed_time":8.724496551,"remaining_time":3.001977308},
{"learn":[0.06874932473],"iteration":744,"passed_time":8.737349039,"remaining_time":2.990636248},
{"learn":[0.06872830307],"iteration":745,"passed_time":8.747836757,"remaining_time":2.978485974},
{"learn":[0.06869110931],"iteration":746,"passed_time":8.759160604,"remaining_time":2.966623337},
{"learn":[0.06864254398],"iteration":747,"passed_time":8.7704395,"remaining_time":2.954746997},
{"learn":[0.06860649379],"iteration":748,"passed_time":8.781688954,"remaining_time":2.942862386},
{"learn":[0.06858496111],"iteration":749,"passed_time":8.792067905,"remaining_time":2.930689302},
{"learn":[0.06856632508],"iteration":750,"passed_time":8.802533092,"remaining_time":2.918549587},
{"learn":[0.06852809556],"iteration":751,"passed_time":8.813632893,"remaining_time":2.906623614},
{"learn":[0.06847909769],"iteration":752,"passed_time":8.824760195,"remaining_time":2.894708855},
{"learn":[0.06846021256],"iteration":753,"passed_time":8.835530262,"remaining_time":2.882679634},
{"learn":[0.06843036726],"iteration":754,"passed_time":8.846698535,"remaining_time":2.870782968},
{"learn":[0.06840584005],"iteration":755,"passed_time":8.857506264,"remaining_time":2.858771863},
{"learn":[0.06833556393],"iteration":756,"passed_time":8.868835486,"remaining_time":2.846931338},
{"learn":[0.06831283251],"iteration":757,"passed_time":8.880240069,"remaining_time":2.835116223},
{"learn":[0.06828477818],"iteration":758,"passed_time":8.891187289,"remaining_time":2.823156965},
{"learn":[0.06827090177],"iteration":759,"passed_time":8.90143789,"remaining_time":2.810980386},
{"learn":[0.06824436528],"iteration":760,"passed_time":8.912850775,"remaining_time":2.799173896},
{"learn":[0.06819757228],"iteration":761,"passed_time":8.924181662,"remaining_time":2.787342829},
{"learn":[0.06816725664],"iteration":762,"passed_time":8.935552982,"remaining_time":2.775525632},
{"learn":[0.06814297316],"iteration":763,"passed_time":8.946579121,"remaining_time":2.763602975},
{"learn":[0.06810561249],"iteration":764,"passed_time":8.958228925,"remaining_time":2.751874245},
{"learn":[0.06807384426],"iteration":765,"passed_time":8.969741137,"remaining_time":2.740103689},
{"learn":[0.06805365766],"iteration":766,"passed_time":8.980146114,"remaining_time":2.72799745},
{"learn":[0.0680179514],"iteration":767,"passed_time":8.991189097,"remaining_time":2.716088373},
{"learn":[0.06798806049],"iteration":768,"passed_time":9.002178601,"remaining_time":2.704165483},
{"learn":[0.06797552654],"iteration":769,"passed_time":9.01252751,"remaining_time":2.692053672},
{"learn":[0.06794388305],"iteration":770,"passed_time":9.023640971,"remaining_time":2.680173518},
{"learn":[0.06789940292],"iteration":771,"passed_time":9.034503872,"remaining_time":2.668221351},
{"learn":[0.0678538655],"iteration":772,"passed_time":9.045047661,"remaining_time":2.656178291},
{"learn":[0.06781753583],"iteration":773,"passed_time":9.056749776,"remaining_time":2.644477325},
{"learn":[0.06781356837],"iteration":774,"passed_time":9.066351779,"remaining_time":2.632166645},
{"learn":[0.06777983922],"iteration":775,"passed_time":9.079443962,"remaining_time":2.620870422},
{"learn":[0.06774809348],"iteration":776,"passed_time":9.092756754,"remaining_time":2.609632891},
{"learn":[0.06770666887],"iteration":777,"passed_time":9.104188797,"remaining_time":2.597853359},
{"learn":[0.06770166745],"iteration":778,"passed_time":9.114268345,"remaining_time":2.585691019},
{"learn":[0.06766173986],"iteration":779,"passed_time":9.125258149,"remaining_time":2.57379076},
{"learn":[0.06762381097],"iteration":780,"passed_time":9.137126403,"remaining_time":2.562139158},
{"learn":[0.06757658271],"iteration":781,"passed_time":9.148603812,"remaining_time":2.550378045},
{"learn":[0.06755262151],"iteration":782,"passed_time":9.159397151,"remaining_time":2.538428074},
{"learn":[0.06752783918],"iteration":783,"passed_time":9.170644198,"remaining_time":2.526606055},
{"learn":[0.06749432651],"iteration":784,"passed_time":9.182126284,"remaining_time":2.514849874},
{"learn":[0.06746354528],"iteration":785,"passed_time":9.192868838,"remaining_time":2.502893042},
{"learn":[0.06745400518],"iteration":786,"passed_time":9.203669888,"remaining_time":2.490955128},
{"learn":[0.0674133289],"iteration":787,"passed_time":9.214990558,"remaining_time":2.479159896},
{"learn":[0.06740687012],"iteration":788,"passed_time":9.224411661,"remaining_time":2.466857871},
{"learn":[0.06732401904],"iteration":789,"passed_time":9.236201863,"remaining_time":2.4551929},
{"learn":[0.06726308989],"iteration":790,"passed_time":9.247734034,"remaining_time":2.443459435},
{"learn":[0.06721861384],"iteration":791,"passed_time":9.258410186,"remaining_time":2.431501665},
{"learn":[0.06717961353],"iteration":792,"passed_time":9.269394709,"remaining_time":2.419627623},
{"learn":[0.06714822253],"iteration":793,"passed_time":9.280916837,"remaining_time":2.4078953},
{"learn":[0.06713079664],"iteration":794,"passed_time":9.291162423,"remaining_time":2.395834336},
{"learn":[0.06710629199],"iteration":795,"passed_time":9.30237062,"remaining_time":2.384024631},
{"learn":[0.0670777666],"iteration":796,"passed_time":9.31321704,"remaining_time":2.37212429},
{"learn":[0.06705520429],"iteration":797,"passed_time":9.323739127,"remaining_time":2.360144491},
{"learn":[0.06701298517],"iteration":798,"passed_time":9.335217757,"remaining_time":2.348408973},
{"learn":[0.06701040002],"iteration":799,"passed_time":9.345127645,"remaining_time":2.336281911},
{"learn":[0.06694355521],"iteration":800,"passed_time":9.356681798,"remaining_time":2.324568886},
{"learn":[0.06690963084],"iteration":801,"passed_time":9.367896287,"remaining_time":2.3127724},
{"learn":[0.06687146935],"iteration":802,"passed_time":9.379027303,"remaining_time":2.300956885},
{"learn":[0.06684418852],"iteration":803,"passed_time":9.390186613,"remaining_time":2.28914997},
{"learn":[0.06680637886],"iteration":804,"passed_time":9.401652495,"remaining_time":2.277418927},
{"learn":[0.0667646368],"iteration":805,"passed_time":9.413563066,"remaining_time":2.265795577},
{"learn":[0.06673416501],"iteration":806,"passed_time":9.424262005,"remaining_time":2.253881743},
{"learn":[0.06669348616],"iteration":807,"passed_time":9.435775335,"remaining_time":2.242164436},
{"learn":[0.06665715909],"iteration":808,"passed_time":9.447164735,"remaining_time":2.230418374},
{"learn":[0.06664245567],"iteration":809,"passed_time":9.457625768,"remaining_time":2.218455427},
{"learn":[0.06661347103],"iteration":810,"passed_time":9.468622933,"remaining_time":2.206621127},
{"learn":[0.06660953725],"iteration":811,"passed_time":9.477925425,"remaining_time":2.194396527},
{"learn":[0.066581287],"iteration":812,"passed_time":9.489002606,"remaining_time":2.182587315},
{"learn":[0.06655620254],"iteration":813,"passed_time":9.499920037,"remaining_time":2.170743399},
{"learn":[0.06653824748],"iteration":814,"passed_time":9.510532236,"remaining_time":2.158832471},
{"learn":[0.0664922256],"iteration":815,"passed_time":9.522602572,"remaining_time":2.147253521},
{"learn":[0.06639345407],"iteration":816,"passed_time":9.534597377,"remaining_time":2.135656451},
{"learn":[0.06636486628],"iteration":817,"passed_time":9.545219618,"remaining_time":2.12375302},
{"learn":[0.06634204297],"iteration":818,"passed_time":9.555638308,"remaining_time":2.111807734},
{"learn":[0.06631771319],"iteration":819,"passed_time":9.566391406,"remaining_time":2.099939577},
{"learn":[0.06628774922],"iteration":820,"passed_time":9.577604953,"remaining_time":2.088174527},
{"learn":[0.06620957701],"iteration":821,"passed_time":9.588990896,"remaining_time":2.07644815},
{"learn":[0.06619710207],"iteration":822,"passed_time":9.599392943,"remaining_time":2.064510997},
{"learn":[0.06614992504],"iteration":823,"passed_time":9.61084278,"remaining_time":2.05280137},
{"learn":[0.06612429912],"iteration":824,"passed_time":9.621617276,"remaining_time":2.040949119},
{"learn":[0.06605699221],"iteration":825,"passed_time":9.633610953,"remaining_time":2.029356302},
{"learn":[0.06605261275],"iteration":826,"passed_time":9.643679786,"remaining_time":2.017359858},
{"learn":[0.06601852005],"iteration":827,"passed_time":9.654913416,"remaining_time":2.005610033},
{"learn":[0.06598682518],"iteration":828,"passed_time":9.666010465,"remaining_time":1.99383328},
{"learn":[0.06595029341],"iteration":829,"passed_time":9.676951661,"remaining_time":1.982026244},
{"learn":[0.06590860023],"iteration":830,"passed_time":9.688299734,"remaining_time":1.970304037},
{"learn":[0.06587620623],"iteration":831,"passed_time":9.699160019,"remaining_time":1.958484235},
{"learn":[0.06585839171],"iteration":832,"passed_time":9.710763492,"remaining_time":1.94681573},
{"learn":[0.0658312785],"iteration":833,"passed_time":9.72375428,"remaining_time":1.935423514},
{"learn":[0.06579771478],"iteration":834,"passed_time":9.735457886,"remaining_time":1.923773115},
{"learn":[0.06577687759],"iteration":835,"passed_time":9.746366064,"remaining_time":1.911966548},
{"learn":[0.06575396642],"iteration":836,"passed_time":9.757479702,"remaining_time":1.90020214},
{"learn":[0.06566945821],"iteration":837,"passed_time":9.769042315,"remaining_time":1.88852608},
{"learn":[0.06561499475],"iteration":838,"passed_time":9.780588908,"remaining_time":1.876847216},
{"learn":[0.06557765481],"iteration":839,"passed_time":9.792067734,"remaining_time":1.865155759},
{"learn":[0.0655437841],"iteration":840,"passed_time":9.803208411,"remaining_time":1.853400877},
{"learn":[0.06552196697],"iteration":841,"passed_time":9.814007317,"remaining_time":1.841583321},
{"learn":[0.06550223848],"iteration":842,"passed_time":9.824399167,"remaining_time":1.829692372},
{"learn":[0.06547868323],"iteration":843,"passed_time":9.835130857,"remaining_time":1.817867789},
{"learn":[0.06544316891],"iteration":844,"passed_time":9.84630199,"remaining_time":1.806126401},
{"learn":[0.0654232108],"iteration":845,"passed_time":9.857191391,"remaining_time":1.794335076},
{"learn":[0.06539376258],"iteration":846,"passed_time":9.868204411,"remaining_time":1.782568211},
{"learn":[0.06535272611],"iteration":847,"passed_time":9.879137244,"remaining_time":1.770788751},
{"learn":[0.06531744191],"iteration":848,"passed_time":9.890392985,"remaining_time":1.759068717},
{"learn":[0.06527160255],"iteration":849,"passed_time":9.902228278,"remaining_time":1.747452049},
{"learn":[0.06522849414],"iteration":850,"passed_time":9.913779335,"remaining_time":1.735785101},
{"learn":[0.06519833758],"iteration":851,"passed_time":9.924006195,"remaining_time":1.7238884},
{"learn":[0.06518597372],"iteration":852,"passed_time":9.934590618,"remaining_time":1.712057234},
{"learn":[0.06513256882],"iteration":853,"passed_time":9.946597144,"remaining_time":1.700472111},
{"learn":[0.06510938378],"iteration":854,"passed_time":9.957845828,"remaining_time":1.68875748},
{"learn":[0.06508074468],"iteration":855,"passed_time":9.968473329,"remaining_time":1.676939439},
{"learn":[0.06505333749],"iteration":856,"passed_time":9.979686692,"remaining_time":1.665221933},
{"learn":[0.06502172341],"iteration":857,"passed_time":9.99042319,"remaining_time":1.653426682},
{"learn":[0.06498459065],"iteration":858,"passed_time":10.00171459,"remaining_time":1.641724979},
{"learn":[0.06496936101],"iteration":859,"passed_time":10.01270159,"remaining_time":1.629974677},
{"learn":[0.06493789197],"iteration":860,"passed_time":10.02411083,"remaining_time":1.618294316},
{"learn":[0.06490759289],"iteration":861,"passed_time":10.03525568,"remaining_time":1.606572255},
{"learn":[0.06487144409],"iteration":862,"passed_time":10.04655406,"remaining_time":1.594875905},
{"learn":[0.06485121275],"iteration":863,"passed_time":10.05748613,"remaining_time":1.583122817},
{"learn":[0.06481776952],"iteration":864,"passed_time":10.0718686,"remaining_time":1.571910128},
{"learn":[0.06479825482],"iteration":865,"passed_time":10.08330741,"remaining_time":1.560234633},
{"learn":[0.06476675899],"iteration":866,"passed_time":10.09465677,"remaining_time":1.548545964},
{"learn":[0.06475040592],"iteration":867,"passed_time":10.10597606,"remaining_time":1.536853502},
{"learn":[0.06471529265],"iteration":868,"passed_time":10.11749759,"remaining_time":1.525192387},
{"learn":[0.06465980318],"iteration":869,"passed_time":10.12878199,"remaining_time":1.513496159},
{"learn":[0.06462195358],"iteration":870,"passed_time":10.1401145,"remaining_time":1.501808003},
{"learn":[0.06459278597],"iteration":871,"passed_time":10.15130455,"remaining_time":1.49009975},
{"learn":[0.06456720711],"iteration":872,"passed_time":10.16232386,"remaining_time":1.478367847},
{"learn":[0.06454742612],"iteration":873,"passed_time":10.17282803,"remaining_time":1.466563309},
{"learn":[0.06454735669],"iteration":874,"passed_time":10.18089632,"remaining_time":1.454413759},
{"learn":[0.06450850972],"iteration":875,"passed_time":10.19203523,"remaining_time":1.442708184},
{"learn":[0.06449886674],"iteration":876,"passed_time":10.20233596,"remaining_time":1.430886344},
{"learn":[0.06448400694],"iteration":877,"passed_time":10.21264897,"remaining_time":1.419069674},
{"learn":[0.06447827801],"iteration":878,"passed_time":10.22250028,"remaining_time":1.407192872},
{"learn":[0.06446130369],"iteration":879,"passed_time":10.23302197,"remaining_time":1.395412087},
{"learn":[0.06444067303],"iteration":880,"passed_time":10.24391312,"remaining_time":1.383684065},
{"learn":[0.06439132398],"iteration":881,"passed_time":10.25552917,"remaining_time":1.372054922},
{"learn":[0.0643708627],"iteration":882,"passed_time":10.26644431,"remaining_time":1.360332938},
{"learn":[0.06434004405],"iteration":883,"passed_time":10.27889581,"remaining_time":1.348814382},
{"learn":[0.06433453659],"iteration":884,"passed_time":10.28914547,"remaining_time":1.337007603},
{"learn":[0.06427439648],"iteration":885,"passed_time":10.30037779,"remaining_time":1.325330777},
{"learn":[0.0642351518],"iteration":886,"passed_time":10.31217819,"remaining_time":1.313727324},
{"learn":[0.06421112826],"iteration":887,"passed_time":10.32315009,"remaining_time":1.30201893},
{"learn":[0.06415570832],"iteration":888,"passed_time":10.33600778,"remaining_time":1.290547653},
{"learn":[0.06411809195],"iteration":889,"passed_time":10.34876528,"remaining_time":1.279060878},
{"learn":[0.06409400515],"iteration":890,"passed_time":10.35985938,"remaining_time":1.267367758},
{"learn":[0.06407408747],"iteration":891,"passed_time":10.37080073,"remaining_time":1.255657488},
{"learn":[0.06403162041],"iteration":892,"passed_time":10.38254839,"remaining_time":1.244045551},
{"learn":[0.06398481625],"iteration":893,"passed_time":10.39414012,"remaining_time":1.232414824},
{"learn":[0.06396889841],"iteration":894,"passed_time":10.40508576,"remaining_time":1.220708385},
{"learn":[0.06394043094],"iteration":895,"passed_time":10.41604837,"remaining_time":1.209005615},
{"learn":[0.06391112623],"iteration":896,"passed_time":10.42721466,"remaining_time":1.197327882},
{"learn":[0.06388648052],"iteration":897,"passed_time":10.43810326,"remaining_time":1.185619747},
{"learn":[0.06385445772],"iteration":898,"passed_time":10.4495887,"remaining_time":1.173980488},
{"learn":[0.06380240336],"iteration":899,"passed_time":10.46109859,"remaining_time":1.162344288},
{"learn":[0.06377873053],"iteration":900,"passed_time":10.47214689,"remaining_time":1.150657649},
{"learn":[0.06376101571],"iteration":901,"passed_time":10.48279964,"remaining_time":1.138929451},
{"learn":[0.06372734486],"iteration":902,"passed_time":10.49390729,"remaining_time":1.1272525},
{"learn":[0.06372125866],"iteration":903,"passed_time":10.50368605,"remaining_time":1.115435687},
{"learn":[0.06368008152],"iteration":904,"passed_time":10.51527579,"remaining_time":1.103813481},
{"learn":[0.06365192835],"iteration":905,"passed_time":10.52649621,"remaining_time":1.092153028},
{"learn":[0.06364782355],"iteration":906,"passed_time":10.5364422,"remaining_time":1.080362871},
{"learn":[0.06362930857],"iteration":907,"passed_time":10.5476249,"remaining_time":1.068702083},
{"learn":[0.06362359473],"iteration":908,"passed_time":10.55771965,"remaining_time":1.056933431},
{"learn":[0.06361790357],"iteration":909,"passed_time":10.56757782,"remaining_time":1.045145059},
{"learn":[0.06357795915],"iteration":910,"passed_time":10.57840157,"remaining_time":1.033455258},
{"learn":[0.06356787246],"iteration":911,"passed_time":10.58846928,"remaining_time":1.021694405},
{"learn":[0.06352876034],"iteration":912,"passed_time":10.6002967,"remaining_time":1.010104943},
{"learn":[0.06348710155],"iteration":913,"passed_time":10.61170569,"remaining_time":0.9984755898},
{"learn":[0.06348385711],"iteration":914,"passed_time":10.62162132,"remaining_time":0.9867079915},
{"learn":[0.06345593525],"iteration":915,"passed_time":10.63318209,"remaining_time":0.975095301},
{"learn":[0.06341091528],"iteration":916,"passed_time":10.64426711,"remaining_time":0.9634396618},
{"learn":[0.06339967719],"iteration":917,"passed_time":10.65504256,"remaining_time":0.9517576139},
{"learn":[0.06338053293],"iteration":918,"passed_time":10.66579375,"remaining_time":0.9400754011},
{"learn":[0.0633393529],"iteration":919,"passed_time":10.67720215,"remaining_time":0.9284523608},
{"learn":[0.06330495213],"iteration":920,"passed_time":10.688175,"remaining_time":0.9167924265},
{"learn":[0.06327502443],"iteration":921,"passed_time":10.70031126,"remaining_time":0.9052324057},
{"learn":[0.06323573005],"iteration":922,"passed_time":10.71235866,"remaining_time":0.8936637233},
{"learn":[0.06318149884],"iteration":923,"passed_time":10.72517039,"remaining_time":0.8821568715},
{"learn":[0.06314407393],"iteration":924,"passed_time":10.73679438,"remaining_time":0.8705508954},
{"learn":[0.06311323831],"iteration":925,"passed_time":10.74801628,"remaining_time":0.8589127484},
{"learn":[0.06307547548],"iteration":926,"passed_time":10.75843107,"remaining_time":0.84721194},
{"learn":[0.06301429368],"iteration":927,"passed_time":10.76964985,"remaining_time":0.8355762816},
{"learn":[0.06296913871],"iteration":928,"passed_time":10.78095116,"remaining_time":0.823947828},
{"learn":[0.06293384171],"iteration":929,"passed_time":10.7929875,"remaining_time":0.8123754032},
{"learn":[0.06291006112],"iteration":930,"passed_time":10.80445976,"remaining_time":0.8007601753},
{"learn":[0.06288141582],"iteration":931,"passed_time":10.8160484,"remaining_time":0.7891537462},
{"learn":[0.06285080386],"iteration":932,"passed_time":10.82725898,"remaining_time":0.7775202051},
{"learn":[0.06281506537],"iteration":933,"passed_time":10.83854329,"remaining_time":0.7658927806},
{"learn":[0.0627854763],"iteration":934,"passed_time":10.84910977,"remaining_time":0.7542161873},
{"learn":[0.06276283225],"iteration":935,"passed_time":10.86031572,"remaining_time":0.74258569},
{"learn":[0.06272762937],"iteration":936,"passed_time":10.87209318,"remaining_time":0.7309945256},
{"learn":[0.06270788088],"iteration":937,"passed_time":10.88307463,"remaining_time":0.7193503487},
{"learn":[0.06269688996],"iteration":938,"passed_time":10.89376949,"remaining_time":0.7076889659},
{"learn":[0.06265698624],"iteration":939,"passed_time":10.90503982,"remaining_time":0.6960663714},
{"learn":[0.06263721811],"iteration":940,"passed_time":10.91575209,"remaining_time":0.6844095361},
{"learn":[0.06262905155],"iteration":941,"passed_time":10.92576679,"remaining_time":0.6727117557},
{"learn":[0.06258749746],"iteration":942,"passed_time":10.93722944,"remaining_time":0.6611050668},
{"learn":[0.06254980924],"iteration":943,"passed_time":10.94870972,"remaining_time":0.6494997293},
{"learn":[0.06251170345],"iteration":944,"passed_time":10.96034514,"remaining_time":0.6379036856},
{"learn":[0.06248348104],"iteration":945,"passed_time":10.97095111,"remaining_time":0.6262487951},
{"learn":[0.0624474119],"iteration":946,"passed_time":10.98249298,"remaining_time":0.6146484982},
{"learn":[0.06244458238],"iteration":947,"passed_time":10.99195522,"remaining_time":0.6029342527},
{"learn":[0.0624128779],"iteration":948,"passed_time":11.00346802,"remaining_time":0.5913349515},
{"learn":[0.06238164183],"iteration":949,"passed_time":11.01510841,"remaining_time":0.5797425478},
{"learn":[0.06234118139],"iteration":950,"passed_time":11.02638526,"remaining_time":0.5681313119},
{"learn":[0.06230825223],"iteration":951,"passed_time":11.03841162,"remaining_time":0.5565585692},
{"learn":[0.06228845087],"iteration":952,"passed_time":11.04981956,"remaining_time":0.5449543747},
{"learn":[0.06225677814],"iteration":953,"passed_time":11.06214824,"remaining_time":0.5333949884},
{"learn":[0.06223294441],"iteration":954,"passed_time":11.0748353,"remaining_time":0.5218508779},
{"learn":[0.06220138536],"iteration":955,"passed_time":11.08688404,"remaining_time":0.5102749977},
{"learn":[0.06217569884],"iteration":956,"passed_time":11.0979971,"remaining_time":0.4986560872},
{"learn":[0.06215935212],"iteration":957,"passed_time":11.10880449,"remaining_time":0.4870248317},
{"learn":[0.06213700441],"iteration":958,"passed_time":11.11975075,"remaining_time":0.4754012312},
{"learn":[0.06210661466],"iteration":959,"passed_time":11.13096998,"remaining_time":0.4637904158},
{"learn":[0.06208942598],"iteration":960,"passed_time":11.14196975,"remaining_time":0.4521715092},
{"learn":[0.06206563021],"iteration":961,"passed_time":11.15320503,"remaining_time":0.4405631923},
{"learn":[0.06203440839],"iteration":962,"passed_time":11.16456238,"remaining_time":0.4289603407},
{"learn":[0.06201333863],"iteration":963,"passed_time":11.17585374,"remaining_time":0.4173555338},
{"learn":[0.06201330627],"iteration":964,"passed_time":11.18399361,"remaining_time":0.4056370738},
{"learn":[0.06200321512],"iteration":965,"passed_time":11.19487197,"remaining_time":0.3940224088},
{"learn":[0.06198712761],"iteration":966,"passed_time":11.20586695,"remaining_time":0.3824132465},
{"learn":[0.06195119409],"iteration":967,"passed_time":11.21736731,"remaining_time":0.3708220598},
{"learn":[0.06190569196],"iteration":968,"passed_time":11.22901983,"remaining_time":0.3592359286},
{"learn":[0.06189050327],"iteration":969,"passed_time":11.23970575,"remaining_time":0.3476197656},
{"learn":[0.06185943457],"iteration":970,"passed_time":11.25084051,"remaining_time":0.3360189234},
{"learn":[0.0618146446],"iteration":971,"passed_time":11.26249711,"remaining_time":0.324434073},
{"learn":[0.06177451249],"iteration":972,"passed_time":11.27348788,"remaining_time":0.312830599},
{"learn":[0.06174548124],"iteration":973,"passed_time":11.28467256,"remaining_time":0.301233559},
{"learn":[0.06170670621],"iteration":974,"passed_time":11.29650401,"remaining_time":0.2896539489},
{"learn":[0.06169223855],"iteration":975,"passed_time":11.30640067,"remaining_time":0.278026246},
{"learn":[0.06167310866],"iteration":976,"passed_time":11.31736783,"remaining_time":0.2664272877},
{"learn":[0.0616515352],"iteration":977,"passed_time":11.32894248,"remaining_time":0.2548432869},
{"learn":[0.06162285639],"iteration":978,"passed_time":11.34130825,"remaining_time":0.2432762751},
{"learn":[0.06158665627],"iteration":979,"passed_time":11.35300981,"remaining_time":0.2316940777},
{"learn":[0.06154542861],"iteration":980,"passed_time":11.36448436,"remaining_time":0.2201072404},
{"learn":[0.06154007287],"iteration":981,"passed_time":11.37441102,"remaining_time":0.2084922591},
{"learn":[0.06152226739],"iteration":982,"passed_time":11.3853967,"remaining_time":0.1968990274},
{"learn":[0.06150069761],"iteration":983,"passed_time":11.39688389,"remaining_time":0.1853151852},
{"learn":[0.06148307729],"iteration":984,"passed_time":11.40823685,"remaining_time":0.1737294952},
{"learn":[0.06144381643],"iteration":985,"passed_time":11.42063055,"remaining_time":0.1621590544},
{"learn":[0.06140672652],"iteration":986,"passed_time":11.4317322,"remaining_time":0.1505699277},
{"learn":[0.06138946172],"iteration":987,"passed_time":11.44199968,"remaining_time":0.138971656},
{"learn":[0.0613418627],"iteration":988,"passed_time":11.45327827,"remaining_time":0.1273873215},
{"learn":[0.0613089151],"iteration":989,"passed_time":11.46479738,"remaining_time":0.1158060341},
{"learn":[0.06126491624],"iteration":990,"passed_time":11.47682782,"remaining_time":0.1042295161},
{"learn":[0.06124001078],"iteration":991,"passed_time":11.48886954,"remaining_time":0.09265217373},
{"learn":[0.06122113863],"iteration":992,"passed_time":11.5002772,"remaining_time":0.08106942642},
{"learn":[0.06120431725],"iteration":993,"passed_time":11.51098498,"remaining_time":0.06948280674},
{"learn":[0.06117186831],"iteration":994,"passed_time":11.52285394,"remaining_time":0.05790378864},
{"learn":[0.06111398451],"iteration":995,"passed_time":11.53457361,"remaining_time":0.04632358881},
{"learn":[0.0610954726],"iteration":996,"passed_time":11.54593049,"remaining_time":0.03474201754},
{"learn":[0.06108081069],"iteration":997,"passed_time":11.55642048,"remaining_time":0.02315915929},
{"learn":[0.0610457625],"iteration":998,"passed_time":11.56763477,"remaining_time":0.01157921398},
{"learn":[0.06102938046],"iteration":999,"passed_time":11.57807393,"remaining_time":0}
]}